Workbook
Name \C: #REF!
Name \C: #REF!
Name \D: #REF!
Name \P: #REF!
Name _QER1: file
Name _QER1: file
Name _QER1: file
Name _R: file
Name _R: file
Name _R: file
Name _Rendimento: #REF!
Name _rev.: #REF!
Name a: file
Name a: file
Name a: file
Name A_DAut_Aut: #REF!
Name A_DAut_Aut: #REF!
Name A_IMPRESI_N_IM: #REF!
Name A1_Período_1: #REF!
Name aaaaaaaa: file
Name aaaaaaaa: file
Name aaaaaaaa: file
Name AAAAAAAAAA: file
Name AAAAAAAAAA: file
Name AAAAAAAAAA: file
Name AAAAAAAAAAAAAA: #REF!
Name AAAAAAAAAAAAAA: #REF!
Name ADF: file
Name ADF: file
Name ADF: file
Name ADFA: file
Name ADFA: file
Name ADFA: file
Name ADFADFA: #REF!
Name ADFADFA: #REF!
Name adfea: #REF!
Name ADIC1: #REF!
Name ADSF: file
Name ADSF: file
Name ADSF: file
Name aeaaf: #REF!
Name aeaaf: #REF!
Name aeae: file
Name aeae: file
Name aeae: file
Name aeasef: #REF!
Name aeasef: #REF!
Name aegdftj: #REF!
Name aerq: file
Name aerq: file
Name aerq: file
Name AFDA: #REF!
Name afdvvc: #REF!
Name AFFFFFE: file
Name AFFFFFE: file
Name AFFFFFE: file
Name Afloramento: #REF!
Name Afloramento: #REF!
Name AfloramentoMáximo: #REF!
Name AfloramentoMedio: #REF!

Sheet Diario de obra
E2: RELATÓRIO DIÁRIO DE OBRA | T2: =LOWER(S2)
B3: ='RDO - Efetivo - Equipamento'!C1 -> OBRA 0474 LT 500 kV TERMINAL RIO - LAGOS
B4: PRAZO CONTRATUAL | E4: DATA | H4: DIA DA SEMANA | K4: RDO No.: | L4: ="LT-L-TRIO-LGO-RD-A4-000"&'RDO - Efetivo - Equipamento'!CA1 -> LT-L-TRIO-LGO-RD-A4-00052 | O4: Revisão: | P4: 0A
B5: ='RDO - Efetivo - Equipamento'!AJ3&" DIAS" -> 219 DIAS | E5: ='RDO - Efetivo - Equipamento'!CA3 -> 45424 | H5: =TEXT(E5,"dddd") -> domingo
B7: ITEM | C7: ATIVIDADE | G7: UND | H7: ="EXECUTADO EM "&(TEXT(E5,"dd/mm/aa")) -> EXECUTADO EM 12/05/24 | N7: QTD Prevista | O7: Realizado QTD | P7: Realizado Acumulado QTD
B8: 1.0 | C8: SERVIÇOS PRELIMINARES | G8: -
B9: 1.3 | C9: CONFERÊNCIA DE PERFIL | G9: Km | N9: 118.46333 | P9: 62.93161
B10: 1.4 | C10: RE-CONFERÊNCIA TOPOGRÁFICA | G10: Torre | N10: 118.46333 | P10: 0
B11: 1.5 | C11: SEÇÃO DIAGONAL | G11: Torre | N11: 252 | P11: 10
B12: 1.6 | C12: MARCAÇÃO DE CAVAS / PONTOS DE FINCAMENTO | G12: Torre | N12: 252 | P12: 107
B13: 1.7 | C13: RE-MARCAÇÃO DE CAVAS / PONTOS DE FINCAMENTO | G13: Torre | N13: 252 | P13: 0
B14: 2.0 | C14: DESMATAMENTO E ACESSOS | G14: -
B15: 2.1 | C15: SUPRESSÃO VEGETAL (ÁREA DA TORRE) | G15: Km | N15: 252 | P15: 87
B16: 2.2 | C16: SUPRESSÃO VEGETAL (FAIXA DE SERVIÇO) | G16: Km | N16: 118.46333 | P16: 0
B17: 2.3 | C17: SUPRESSÃO VEGETAL (CORTE SELETIVO) | G17: Km | N17: 118.46333 | P17: 0
B18: 2.2 | C18: ABERTURA DE ACESSOS | G18: Km | N18: 118.46333 | P18: 28.17012
B19: 2.3 | C19: RECUPERAÇÃO DE ACESSOS | G19: Torre | N19: 118.46333 | P19: 2.555
B20: 2.4 | C20: CONFERÊNCIA DE CROQUI DE ACESSO | G20: Torre | N20: 252 | P20: 87
B21: 3.0 | C21: FUNDAÇÃO DE ESTRUTURAS | G21: -
B22: 3.1 | C22: FUNDAÇÃO DE TORRES ESTAIADAS | G22: -
B23: 3.1.1 | C23: ARMAÇÃO MASTRO CENTRAL | G23: Torre | N23: 47 | P23: 20
B24: 3.1.2 | C24: ARMAÇÃO ESTAIS | G24: Torre | N24: 47 | P24: 22
B25: 3.1.3 | C25: CRAVAÇÃO DE ESTACAS METÁLICAS MASTROS | G25: Torre | N25: 47 | P25: 12
B26: 3.1.4 | C26: CRAVAÇÃO DE ESTACAS METÁLICAS ESTAIS | G26: Torre | N26: 47 | P26: 0
B27: 3.1.5 | C27: ESCAVAÇÃO MASTRO CENTRAL | G27: Torre | N27: 47 | P27: 20
B28: 3.1.6 | C28: ESCAVAÇÃO ESTAIS | G28: Torre | N28: 47 | P28: 21
B29: 3.1.7 | C29: NIVELAMENTO / PREPARAÇÃO MASTRO CENTRAL | G29: Torre | N29: 47 | P29: 20
B30: 3.1.8 | C30: NIVELAMENTO / PREPARAÇÃO ESTAIS | G30: Torre | N30: 47 | P30: 21
B31: 3.1.9 | C31: CONCRETAGEM MASTRO CENTRAL | G31: Torre | N31: 47 | P31: 20
B32: 3.1.10 | C32: CONCRETAGEM ESTAIS | G32: Torre | N32: 47 | P32: 20
B33: 3.1.11 | C33: REATERRO MASTRO CENTRAL | G33: Torre | N33: 47 | P33: 20
B34: 3.1.12 | C34: REATERRO ESTAIS | G34: Torre | N34: 47 | P34: 20
B35: 3.1.13 | C35: ENSAIO DE ARRANCAMENTO DE ESTAIS | G35: Torre | N35: 47 | P35: 0
B36: 3.2 | C36: FUNDAÇÃO DE TORRES AUTOPORTANTES | G36: - | P36: 0
B37: 3.2.1 | C37: ARMAÇÃO AUTOPORTANTES | G37: Torre | N37: 208 | P37: 31
B38: 3.2.2 | C38: CRAVAÇÃO DE ESTACAS | G38: Torre | N38: 208 | P38: 0
B39: 3.2.3 | C39: ESCAVAÇÃO AUTOPORTANTES | G39: Torre | N39: 208 | P39: 27
B40: 3.2.4 | C40: NIVELAMENTO / PREPARAÇÃO AUTOPORTANTES | G40: Torre | N40: 208 | O40: 0 | P40: 26
B41: 3.2.5 | C41: CONCRETAGEM AUTOPORTANTES | G41: Torre | N41: 208 | P41: 26
B42: 3.2.6 | C42: REATERRO | G42: Torre | N42: 208 | P42: 26
B43: 3.3 | C43: FUNDAÇÃO CONCLUÍDA | G43: Torre
B44: 4.0 | C44: SISTEMA DE ATERRAMENTO | G44: -
B45: 4.1 | C45: INSTALAÇÃO DO CABO CONTRAPESO | G45: Torre
B46: 4.2 | C46: MEDIÇÃO DE RESISTÊNCIA DO ATERRAMENTO | G46: Km
B47: 4.3 | C47: ATERRAMENTO / SECCIONAMENTO DE CERCAS | G47: Km
B48: 5.0 | C48: MONTAGEM DE ESTRUTURAS | G48: -
B49: 5.1 | C49: MONTAGEM DE TORRES ESTAIADAS | G49: Torre
B50: 5.1.1 | C50: DISTRIBUIÇÃO / TRANSPORTE DE ESTRUTURAS ESTAIADAS | G50: Torre
B51: 5.1.2 | C51: PRÉ-MONTAGEM EM SOLO ESTAIADAS | G51: Torre
B52: 5.1.3 | C52: MONTAGEM / IÇAMENTO ESTAIADAS | G52: Torre
B53: 5.1.4 | C53: REVISÃO / RET. FLAMBAGEM ESTAIADAS | G53: Torre
B54: 5.1.5 | C54: GIRO E PRUMO ESTAIADAS | G54: Torre
... B100: 9.4 | C100: TESTE PONTA A PONTA DO CABO OPGW | G100: Km
B101: ESPAÇO PARA REGISTROS DE PENDÊNCIAS, ADVERTÊNCIAS, ORDENS DE SERVIÇO, ESCLARECIMENTOS E COMENTÁRIOS | S101: =LOWER(R101)
B103: COMENTÁRIOS E OBS. FASTTEL
B108: COMENTÁRIOS E OBS. NEOENERGIA
B125: EMPRESA | K125: FISCALIZAÇÂO
B126: DATA: | C126: =+E5 -> 45424 | K126: DATA: | L126: =C126 -> 45424
E127: Assinatura Fasttel | M127: Assinatura Neoenergia

Sheet RDO - Efetivo - Equipamento
C1: OBRA 0474 LT 500 kV TERMINAL RIO - LAGOS | AF1: Data de início: | AJ1: 45373 | BW1: RDO No.: | CA1: =VLOOKUP(CA3,Datas!B2:C1369,2,0) -> 52
AF2: Data de término: | AJ2: 45592 | AP2: HORÁRIO DE TRABALHO
AF3: Prazo contratual: | AJ3: =AJ2-AJ1 -> 219 | AL3: dias | AP3: Segunda a Quinta | BN3: 07h/12h e 13h/17h | BW3: Data: | CA3: 45424
AF4: Tempo decorrido: | AJ4: =CA3-AJ1+1 -> 52 | AL4: dias | AP4: Sexta | BN4: 07h/12h e 13h/16h | BW4: Dia da Semana: | CA4: =TEXT(CA3,"dddd") -> domingo
AF5: Tempo restante: | AJ5: =+AJ3-AJ4 -> 167 | AL5: dias | AP5: Sab./Dom./Feriado: | BN5: 07h/11h | BW5: Local: | BY5: PATY DE ALFERES
A7: QUADRO DE EFETIVO POR EQUIPE
A9: ITEM | B9: FUNÇÃO | C9: INDIRETOS | M9: DIRETOS | BO9: SUBEMPREITEIROS | BX9: TOTAL SUBEMPREITEIROS | BY9: OUTROS | CB9: TOTAL GERAL
BG10: =+Planilha8!BI3 -> 0 | BH10: =+Planilha8!BJ3 -> 0 | BI10: =+Planilha8!BK3 -> 0 | BJ10: =+Planilha8!BL3 -> 0 | BK10: =+Planilha8!BM3 -> 0 | BM10: TOITAL | BR10: =+Planilha8!W9 -> 0 | BS10: =+Planilha8!X9 -> 0 | BT10: =+Planilha8!Y9 -> 0 | BU10: =+Planilha8!Z9 -> 0 | BV10: =+Planilha8!AA9 -> 0 | BW10: =+Planilha8!AB9 -> 0 | BY10: =+Planilha8!J5 -> AFASTADOS / INSS / LICENÇA | BZ10: =+Planilha8!K5 -> FÉRIAS | CA10: =+Planilha8!L5 -> 0
BL11: =AP11+1 -> 1 | BO11: 1 | BP11: 2 | BQ11: 3 | BR11: 4
A13: 1 | BM13: =SUM(C13:BL13) -> 0
A14: =A13+1 -> 2 | BM14: =SUM(C14:BL14) -> 0
A15: =A14+1 -> 3 | BM15: =SUM(C15:BL15) -> 0
A16: =A15+1 -> 4 | BM16: =SUM(C16:BL16) -> 0
A17: =A16+1 -> 5 | BM17: =SUM(C17:BL17) -> 0
A18: =A17+1 -> 6 | BM18: =SUM(C18:BL18) -> 0
A19: =A18+1 -> 7 | BM19: =SUM(C19:BL19) -> 0
A20: =A19+1 -> 8 | BM20: =SUM(C20:BL20) -> 0
A21: =A20+1 -> 9 | BM21: =SUM(C21:BL21) -> 0
A22: =A21+1 -> 10 | BM22: =SUM(C22:BL22) -> 0
A23: =A22+1 -> 11 | BM23: =SUM(C23:BL23) -> 0
A24: =A23+1 -> 12 | BM24: =SUM(C24:BL24) -> 0
A25: =A24+1 -> 13 | BM25: =SUM(C25:BL25) -> 0
... A112: =A111+1 -> 100 | BM112: =SUM(C112:BL112) -> 0
A113: 150 | BM113: =SUM(C113:BL113) -> 0
A114: TOTAL POR ATIVIDADE | C114: =SUM(C13:C112) -> 0 | D114: =SUM(D13:D112) -> 0 | E114: =SUM(E13:E112) -> 0 | F114: =SUM(F13:F112) -> 0 | G114: =SUM(G13:G112) -> 0 | H114: =SUM(H13:H112) -> 0 | I114: =SUM(I13:I112) -> 0 | J114: =SUM(J13:J112) -> 0 | ... BM114: =SUM(BM13:BM112) -> 0 | BN114: =SUM(G114+BM114) -> 0 | BO114: =SUM(BO13:BO112) -> 0 | BP114: =SUM(BP13:BP112) -> 0 | BQ114: =SUM(BQ13:BQ112) -> 0 | BR114: =SUM(BR13:BR112) -> 0 | BS114: =SUM(BS13:BS112) -> 0 | BT114: =SUM(BT13:BT112) -> 0 | BU114: =SUM(BU13:BU112) -> 0 | BV114: =SUM(BV13:BV112) -> 0 | BW114: =SUM(BW13:BW112) -> 0 | BX114: =SUM(BO114:BW114) -> 0 | BY114: =SUM(BY13:BY112) -> 0 | BZ114: =SUM(BZ13:BZ112) -> 0 | CA114: =SUM(CA13:CA112) -> 0 | CB114: =BX114+BN114+BY114+BZ114+CA114 -> 0
A115: ELABORADO POR: | C115: VISTOS
A116: NOME:
A118: CARGO:
C119: Assinatura FASTTEL | U119: Assinatura Neoenergia
C121: =C1 -> OBRA 0474 LT 500 kV TERMINAL RIO - LAGOS | AF121: Data de início: | AJ121: =AJ1 -> 45373 | AP121: HORÁRIO DE TRABALHO | BW121: RDO No.: | CA121: =CA1 -> 52
AF122: Data de término: | AJ122: =AJ2 -> 45592
AF123: Prazo contratual: | AJ123: =AJ3 -> 219 | AL123: dias | AP123: Segunda a Sexta: | BN123: 07h/12h e 13h/17h | BW123: Data: | CA123: =CA3 -> 45424
AF124: Tempo decorrido: | AJ124: =AJ4 -> 52 | AL124: dias | AP124: Sábado: | BN124: 07h/12h e 13h/16h | BW124: Dia da Semana: | CA124: =CA4 -> domingo
AF125: Tempo restante: | AJ125: =AJ5 -> 167 | AL125: dias | AP125: Domingo/Feriado: | BN125: 07h/11h | BW125: Local: | BY125: LOTE 2.2
A127: QUADRO DE EQUIPAMENTOS POR EQUIPE
A129: ITEM | B129: EQUIPAMENTO | BN129: TOTAL OBRA | BO129: SUBEMPREITEIROS | BX129: TOTAL SUBEMPREITEIROS | BY129: OUTROS | CB129: TOTAL GERAL
C130: FUNDAÇÃO | D130: GESTÃO DE OBRAS | E130: MEIO AMBIENTE | F130: PRELIMINARES | G130: PRODUÇÃO | H130: SEGURANÇA DO TRABALHO | I130: SERVIÇOS GERAIS | J130: TRANSPORTE | AD130: =+AD10 -> 0 | AE130: =+AE10 -> 0 | AF130: =+AF10 -> 0 | AG130: =+AG10 -> 0 | AH130: =+AH10 -> 0 | AI130: =+AI10 -> 0 | AJ130: =+AJ10 -> 0 | AK130: =+AK10 -> 0 | ... BL130: =+BL10 -> 0 | BM130: TOTAL DIRETOS | BO130: =BO10 -> 0 | BP130: =BP10 -> 0 | BQ130: =BQ10 -> 0 | BR130: =BR10 -> 0 | BS130: =BS10 -> 0 | BT130: =BT10 -> 0 | BU130: =BU10 -> 0 | BV130: =BV10 -> 0 | BW130: =BW10 -> 0 | BY130: =BY10 -> AFASTADOS / INSS / LICENÇA | BZ130: =BZ10 -> FÉRIAS | CA130: =CA10 -> 0
A132: 1 | B132: CAMINHÃO 3/4 CABINE SUPLEMENTAR 23L
A133: 2 | B133: CAMINHÃO 6X4 TRUCK PRANCHA | J133: 1
A134: 3 | B134: CAMINHÃO BETONEIRA | C134: 1
A135: 4 | B135: CAMINHÃO PERFURATRIZ
A136: 5 | B136: CAMINHÃO TOCO CABINE SUPLEMENTAR 23L | C136: 1 | F136: 1
A137: 6 | B137: CAMINHÃO TOCO CARROCERIA
A138: 7 | B138: CAMINHÃO TRUCK 6x4 MUNCK 45T | J138: 2
A139: 8 | B139: CAMINHÃO TRUCK 6x4 MUNCK 45T / C SUP 07 P.
A140: 9 | B140: CAMINHONETE 4X2 | I140: 1
A141: 10 | B141: CAMINHONETE 4X4 | D141: 3 | E141: 1 | F141: 1 | G141: 2
A142: 11 | B142: CAMINHONETE AMBULÂNCIA 4X4 | H142: 1
A143: 12 | B143: TRATOR ESTEIRA
A144: 13 | B144: VEICULO LEVE | H144: 1
A145: 14
A146: 15
A147: 16
A148: 17
A149: 18
A150: 19
A151: 20
A152: 21
A153: 22
A154: 23
A155: 24
A156: 25
... A189: 58
A192: TOTAL POR ATIVIDADE | C192: =SUM(C132:C191) -> 2 | D192: =SUM(D132:D191) -> 3 | E192: =SUM(E132:E191) -> 1 | F192: =SUM(F132:F191) -> 2 | G192: =SUM(G132:G191) -> 2 | H192: =SUM(H132:H191) -> 2 | I192: =SUM(I132:I191) -> 1 | J192: =SUM(J132:J191) -> 3 | ... AD192: =SUM(AD132:AD191) -> 0
A193: ELABORADO POR: | C193: VISTOS
A194: NOME:
A196: CARGO:
C197: Assinatura FASTTEL | U197: Assinatura Neoenergia

Sheet Planilha8
F2: CARAPEBUS | G2: CADASTRO | H2: PÁTIO DE MATERIAIS CARAPEBUS
G4: PÁTIO DE MATERIAIS CARAPEBUS | H4: PÁTIO DE MATERIAIS CARAPEBUS
G5: PÁTIO DE MATERIAIS CARAPEBUS | H5: PÁTIO DE MATERIAIS CARAPEBUS | J5: AFASTADOS / INSS / LICENÇA | K5: FÉRIAS
G6: PÁTIO DE MATERIAIS CARAPEBUS | H6: PÁTIO DE MATERIAIS CARAPEBUS
G7: PÁTIO DE MATERIAIS CARAPEBUS | H7: PÁTIO DE MATERIAIS CARAPEBUS | J7: AFASTADOS / INSS / LICENÇA
G8: PÁTIO DE MATERIAIS CARAPEBUS | H8: PÁTIO DE MATERIAIS CARAPEBUS | J8: FÉRIAS
S9: REFEITÓRIO - TERCEIRIZADOS
G10: PÁTIO DE MATERIAIS CARAPEBUS | H10: PÁTIO DE MATERIAIS CARAPEBUS
G11: PÁTIO DE MATERIAIS CARAPEBUS | H11: PÁTIO DE MATERIAIS CARAPEBUS
G12: PÁTIO DE MATERIAIS CARAPEBUS | H12: PÁTIO DE MATERIAIS CARAPEBUS | P12: CRAVAÇÃO DE ESTACAS PRÉ-MOLDADAS (4B) - EQUIPE 1 - TERCEIRIZADOS
G13: PÁTIO DE MATERIAIS CARAPEBUS | H13: PÁTIO DE MATERIAIS CARAPEBUS | P13: REFEITÓRIO - TERCEIRIZADOS
G14: PÁTIO DE MATERIAIS CARAPEBUS | H14: PÁTIO DE MATERIAIS CARAPEBUS
G15: PÁTIO DE MATERIAIS CARAPEBUS | H15: ABERTURA E MANUTENÇÃO DE ACESSOS
G16: ABERTURA E MANUTENÇÃO DE ACESSOS | H16: ABERTURA E MANUTENÇÃO DE ACESSOS
G17: ABERTURA E MANUTENÇÃO DE ACESSOS | H17: ABERTURA E MANUTENÇÃO DE ACESSOS
G18: ABERTURA E MANUTENÇÃO DE ACESSOS | H18: ABERTURA E MANUTENÇÃO DE ACESSOS
G19: ABERTURA E MANUTENÇÃO DE ACESSOS | H19: ABERTURA E MANUTENÇÃO DE ACESSOS
G20: ABERTURA E MANUTENÇÃO DE ACESSOS | H20: ARMAÇÃO (14B, 16B) - EQUIPE 1
G21: ARMAÇÃO (14B, 16B) - EQUIPE 1 | H21: ARMAÇÃO (14B, 16B) - EQUIPE 1
G22: ARMAÇÃO (14B, 16B) - EQUIPE 1 | H22: ARMAÇÃO (14B, 16B) - EQUIPE 1
G26: ARMAÇÃO (14B, 16B) - EQUIPE 1 | H26: ARMAÇÃO (14B, 16B) - EQUIPE 1
G27: ARMAÇÃO (14B, 16B) - EQUIPE 1 | H27: ARMAÇÃO (14B, 16B) - EQUIPE 1
G29: ARMAÇÃO (14B, 16B) - EQUIPE 1 | H29: ARMAÇÃO (14B, 16B) - EQUIPE 1
... G240: TRANSFERÊNCIA - SEMANA VIGENTE | H240: TRANSFERÊNCIA - SEMANA VIGENTE
G241: TRANSFERÊNCIA - SEMANA VIGENTE

Sheet GRUPOS
A1: ID | B1: GRUPO DE ATIVIDADE | D1: ID | E1: FUNÇÃO | G1: ID | H1: FUNÇÃO | J1: ID | K1: FUNÇÃO
A2: 1 | B2: CARAPEBUS | D2: 1 | E2: 1/2 OF. MONTADOR | G2: 1 | H2: AMBULÂNCIA | J2: 1 | K2: CRAVAÇÃO DE ESTACAS PRÉ-MOLDADAS (4B) - EQUIPE 1 - TERCEIRIZADOS
A3: =A2+1 -> 2 | B3: VIGILÂNCIA PATRIMONIAL | D3: =D2+1 -> 2 | E3: AJUDANTE | G3: =G2+1 -> 2 | H3: BATE ESTACA SOBRE ESTEIRAS | J3: 2 | K3: CRAVAÇÃO DE ESTACAS PRÉ-MOLDADAS (4B) - EQUIPE 2 - TERCEIRIZADOS
A4: =A3+1 -> 3 | D4: =D3+1 -> 3 | E4: AJUDANTE BATE ESTACAS | G4: =G3+1 -> 3 | H4: CAMINHÃO 4X2 TOCO C/ GUINDAUTO | J4: 3 | K4: CRAVAÇÃO DE ESTACAS PRÉ-MOLDADAS (4B) - EQUIPE 3 - TERCEIRIZADOS
A5: =A4+1 -> 4 | B5: PÁTIO DE MATERIAIS | D5: =D4+1 -> 4 | E5: AJUDANTE DE COZINHA | G5: =G4+1 -> 4 | H5: CAMINHÃO BASCULANTE 4X4 | J5: 4 | K5: LSA FUNDAÇÕES
A6: =A5+1 -> 5 | B6: APOIO LOGÍSTICO | D6: =D5+1 -> 5 | E6: ALMOXARIFE | G6: =G5+1 -> 5 | H6: CAMINHÃO BASCULANTE 6X4 10³ A 16³ | J6: 5 | K6: VERTICE ENGENHARIA
A7: =A6+1 -> 6 | B7: APOIO CAIXAS DE FUSÃO | D7: =D6+1 -> 6 | E7: ALMOXARIFE III | G7: =G6+1 -> 6 | H7: CAMINHÃO BETONEIRA
A8: =A7+1 -> 7 | B8: LANÇAMENTO CABO PILOTO PARA-RAIO/CONDUTOR | D8: =D7+1 -> 7 | E8: ANALISTA DE CUSTO | G8: =G7+1 -> 7 | H8: CAMINHÃO CABINE AUXILIAR 08 PASSAGEIROS
A9: =A8+1 -> 8 | B9: NIVELAMENTO DE OPGW / 3/8" EHS / DOTTEREL E CABOS CONDUTORES | D9: =D8+1 -> 8 | E9: ANALISTA TECNICO DE MATERIAIS I | G9: =G8+1 -> 8 | H9: CAMINHÃO CABINE AUXILIAR 11 PASSAGEIROS
A10: =A9+1 -> 9 | B10: TRANSPORTE DE BOBINAS / ISOLADORES | D10: =D9+1 -> 9 | E10: ANALISTA TÉCNICO II | G10: =G9+1 -> 9 | H10: CAMINHÃO CABINE AUXILIAR 13 PASSAGEIROS
A11: =A10+1 -> 10 | B11: IÇAMENTO DE BANDOLAS / ISOLADORES | D11: =D10+1 -> 10 | E11: ARMADOR I | G11: =G10+1 -> 10 | H11: CAMINHÃO CABINE AUXILIAR 14 PASSAGEIROS
A12: =A11+1 -> 11 | B12: LANÇAMENTO CONDUTORES - ARRAIA | D12: =D11+1 -> 11 | E12: ARMADOR II | G12: =G11+1 -> 11 | H12: CAMINHÃO CABINE AUXILIAR 23 PASSAGEIROS
A13: =A12+1 -> 12 | B13: RECESSO | D13: =D12+1 -> 12 | E13: ARMADOR III | G13: =G12+1 -> 12 | H13: CAMINHÃO CARROCERIA 4x2
A14: =A13+1 -> 13 | B14: TRANSFERÊNCIA - SEMANA VIGENTE | D14: =D13+1 -> 13 | E14: ASSISTENTE ADMINISTRACAO PESSOAL OBRA PL | G14: =G13+1 -> 13 | H14: CAMINHÃO CARROCERIA 4X2 TOCO C/ GUINDAUTO
A15: =A14+1 -> 14 | D15: =D14+1 -> 14 | E15: ASSISTENTE ADMINISTRATIVO DE OBRA SR | G15: =G14+1 -> 14 | H15: CAMINHÃO CARROCERIA 4X4 C/ GUINDAUTO
A16: =A15+1 -> 15 | D16: =D15+1 -> 15 | E16: ASSISTENTE ADMINISTRATIVO OBRAS JR | G16: =G15+1 -> 15 | H16: CAMINHÃO CARROCERIA 6X2
A17: =A16+1 -> 16 | D17: =D16+1 -> 16 | E17: ASSISTENTE ADMINISTRACAO PESSOAL OBRA SR | G17: =G16+1 -> 16 | H17: CAMINHÃO CARROCERIA 6X2 TRUCK | K17: CRAVAÇÃO DE ESTACAS PRÉ-MOLDADAS (4B) - EQUIPE 1 - TERCEIRIZADOS
A18: =A17+1 -> 17 | D18: =D17+1 -> 17 | E18: ASSISTENTE TECNICO | G18: =G17+1 -> 17 | H18: CAMINHÃO CARROCERIA 6X2 TRUCK C/ GUINDAUTO | K18: CRAVAÇÃO DE ESTACAS PRÉ-MOLDADAS (4B) - EQUIPE 2 - TERCEIRIZADOS
A19: =A18+1 -> 18 | D19: =D18+1 -> 18 | E19: AUXILIAR ADMINISTRATIVO DE OBRA I | G19: =G18+1 -> 18 | H19: CAMINHÃO CARROCERIA 6X4 | K19: CRAVAÇÃO DE ESTACAS PRÉ-MOLDADAS (4B) - EQUIPE 3 - TERCEIRIZADOS
A20: =A19+1 -> 19 | D20: =D19+1 -> 19 | E20: AUXILIAR ADMINISTRATIVO DE OBRA III | G20: =G19+1 -> 19 | H20: CAMINHÃO COMBOIO 4X2 | K20: CRAVAÇÃO DE ESTACAS PRÉ-MOLDADAS (4B) - EQUIPE 4 - TERCEIRIZADOS
A21: =A20+1 -> 20 | D21: =D20+1 -> 20 | E21: AUXILIAR ALMOXARIFADO I | G21: =G20+1 -> 20 | H21: CAMINHÃO MUNCK 23TON 4X4 CABINE AUXR 4P | K21: REFEITÓRIO - TERCEIRIZADOS
A22: =A21+1 -> 21 | D22: =D21+1 -> 21 | E22: AUXILIAR ALMOXARIFE | G22: =G21+1 -> 21 | H22: CAMINHÃO MUNCK 4X4 CABINE AUXILIAR 4P
A23: =A22+1 -> 22 | D23: =D22+1 -> 22 | E23: AUXILIAR DE ALMOXARIFADO | G23: =G22+1 -> 22 | H23: CAMINHÃO MUNCK 6X4 45 TON
A24: =A23+1 -> 23 | D24: =D23+1 -> 23 | E24: AUXILIAR DE ESCRITORIO | G24: =G23+1 -> 23 | H24: CAMINHÃO PERFURATRIZ COM OPERADOR (MANUTENÇÃO)
A25: =A24+1 -> 24 | D25: =D24+1 -> 24 | E25: AUXILIAR DE LIMPEZA | G25: =G24+1 -> 24 | H25: CAMINHÃO PERFURATRIZ SEM OPERADOR
A26: =A25+1 -> 25 | D26: =D25+1 -> 25 | E26: AUXILIAR DE SEGURANÇA DO TRABALHO | G26: =G25+1 -> 25 | H26: CAMINHÃO PIPA
A27: =A26+1 -> 26 | D27: =D26+1 -> 26 | E27: AUXILIAR DE TRANSPORTE | G27: =G26+1 -> 26 | H27: CAMINHÃO PRANCHA 6X2
A28: =A27+1 -> 27 | D28: =D27+1 -> 27 | E28: AUXILIAR SERVICOS GERAIS OBRA | G28: =G27+1 -> 27 | H28: CAMINHÃO PRANCHA 6X4
A29: =A28+1 -> 28 | D29: =D28+1 -> 28 | E29: AUXILIAR TECNICO II | G29: =G28+1 -> 28 | H29: CAMINHÃO PRANCHA 8X4
A30: =A29+1 -> 29 | D30: =D29+1 -> 29 | E30: AUXILIAR TOPOGRAFO | G30: =G29+1 -> 29 | H30: CAMINHONETE CABINE DUPLA 4X4
A31: =A30+1 -> 30 | D31: =D30+1 -> 30 | E31: AUXILIAR TOPOGRAFO III | G31: =G30+1 -> 30 | H31: CAMINHONETE CABINE SIMPLES
A32: =A31+1 -> 31 | D32: =D31+1 -> 31 | E32: CARPINTEIRO | G32: =G31+1 -> 31 | H32: CAMINHONETE CABINE SIMPLES 4X4
A33: =A32+1 -> 32 | D33: =D32+1 -> 32 | E33: CARPINTEIRO I | G33: =G32+1 -> 32 | H33: CAMINHONETE L200 TRITON 4X4
... A50: =A49+1 -> 49 | D50: =D49+1 -> 49 | E50: ENCARREGADO DE ELETRICA | G50: =G49+1 -> 49 | H50: RETROESCAVADEIRA 4X4
A51: 50 | D51: =D50+1 -> 50 | E51: ENCARREGADO DE PATIO DE MATERIAIS II | G51: =G50+1 -> 50 | H51: RETROESCAVADEIRA 4X4 COM PERFURATRIZ
A52: 51 | D52: =D51+1 -> 51 | E52: ENCARREGADO TURMA IV | G52: =G51+1 -> 51 | H52: ROCK DRILL
A53: 52 | D53: =D52+1 -> 52 | E53: ENCARREGADO DE SERVIÇOS GERAIS | G53: =G52+1 -> 52 | H53: TENSIONADOR HIDRÁULICO CABO CONDUTOR (FREIO)
A54: 53 | D54: =D53+1 -> 53 | E54: ENCARREGADO DE TRANSPORTES | G54: =G53+1 -> 53 | H54: TOYOTA CABINE DUPLA
A55: 54 | D55: =D54+1 -> 54 | E55: ENCARREGADO DE TURMA I | G55: =G54+1 -> 54 | H55: TOYOTA JEEPÃO 12 LUGARES
A56: 55 | D56: =D55+1 -> 55 | E56: ENCARREGADO DE TURMA II | G56: 55 | H56: TRATOR SOBRE ESTEIRA
A57: 56 | D57: =D56+1 -> 56 | E57: ENCARREGADO DE TURMA III | G57: 56 | H57: TRATOR SOBRE PNEUS 4X4
D58: =D57+1 -> 57 | E58: ENCARREGADO DE TURMA IV | G58: 57 | H58: VAN 15 LUGARES
D59: =D58+1 -> 58 | E59: ENGENHEIRO AMBIENTAL | G59: 58 | H59: VEICULO LEVE
D60: =D59+1 -> 59 | E60: ENGENHEIRO CIVIL | G60: 59 | H60: VEICULO SUV
D61: =D60+1 -> 60 | E61: ENGENHEIRO DE PLANEJAMENTO I | G61: 60 | H61: CAMINHÃO CAÇAMBA
D62: =D61+1 -> 61 | E62: ENGENHEIRO DE PLANEJAMENTO II
D63: =D62+1 -> 62 | E63: ENGENHEIRO DE PRODUÇÃO I
D64: =D63+1 -> 63 | E64: ENGENHEIRO SEG. DO TRABALHO
D65: =D64+1 -> 64 | E65: ESTOQUISTA
D66: =D65+1 -> 65 | E66: FRENTISTA BATE ESTACA
D67: =D66+1 -> 66 | E67: GESTOR DE OBRAS
D68: =D67+1 -> 67 | E68: LABORATORISTA I
D69: =D68+1 -> 68 | E69: LABORATORISTA III
D70: =D69+1 -> 69 | E70: LIDER DE TURMA
D71: =D70+1 -> 70 | E71: LUBRIFICADOR
D72: =D71+1 -> 71 | E72: MARTELETEIRO
D73: =D72+1 -> 72 | E73: MARTELETEIRO II
... D148: =D147+1 -> 147 | E148: 1/2 OF. PEDREIRO
D149: 148 | E149: SOLDADOR III

Sheet LISTAGEM DE EFETIVO
B2: TOTAL | C2: =COUNTA($D$7:$D$4955)-1 -> 299 | E2: DESLIGADO | F2: =COUNTIF(G8:G942,E2) -> 0 | G2: ATIVOS
C3: 98
J4: DIAS
C5: =IFERROR(LARGE('LISTAGEM DE EFETIVO'!D8:D963,1)+1,0) -> 54534 | D5: 1 | E5: 2 | F5: 3 | H5: 6 | I5: 8 | J5: S
E6: SEMPRE CLICAR EM CLASSIFICAR APÓS ALTERAR MANUALMENTE ESTA PLANILHA | G6: LISTAGEM DE EFETIVO
B7: Aloj./Setor | C7: ITEM | D7: CHAPA | E7: NOME | F7: FUNÇÃO | G7: ATIVIDADE | H7: CANTEIRO | I7: RDO - FRENTE | J7: RDO - Equipamento | K7: RDO - Equipamento | L7: RDO - Equipamento
A8: =A7+1 -> 1 | B8: =IF(G8="DESLIGADO","",IF(#REF!=1,#REF!,IF(#REF!=1,#REF!,IF(#REF!=1,#REF!,IF(#REF!=1,#REF!,""))))) -> #REF! | C8: 1 | D8: PJ - 27 | E8: MENCHOL FREITAS DINIZ | F8: ENGENHEIRO DE PRODUÇÃO I | G8: CARAPEBUS | H8: CARAPEBUS | I8: CARAPEBUS | J8: CAMINHONETE CABINE DUPLA 4X4 | K8: CAMINHONETE CABINE DUPLA 4X4 | L8: {=_xlfn.UNIQUE(K8:K711)} -> CAMINHONETE CABINE DUPLA 4X4
A9: =A8+1 -> 2 | B9: =IF(G9="DESLIGADO","",IF(#REF!=1,#REF!,IF(#REF!=1,#REF!,IF(#REF!=1,#REF!,IF(#REF!=1,#REF!,""))))) -> #REF! | C9: 2 | D9: 1234 | E9: WANDERSON FRANCISCO DE ANDRADE | F9: ENCARREGADO ADMINISTRATIVO OBRAS | G9: CARAPEBUS | H9: CARAPEBUS | I9: CARAPEBUS | L9: 0
B10: =IF(G10="DESLIGADO","",IF(#REF!=1,#REF!,IF(#REF!=1,#REF!,IF(#REF!=1,#REF!,IF(#REF!=1,#REF!,""))))) -> #REF! | C10: 3 | D10: 52073 | E10: LUANA HONORIO PEREIRA DA SILVA | F10: AUXILIAR ADMINISTRATIVO DE OBRA I | G10: CARAPEBUS | H10: CARAPEBUS | I10: CARAPEBUS | L10: CAMINHONETE CABINE SIMPLES
A11: =A10+1 -> 1 | B11: =IF(G11="DESLIGADO","",IF(#REF!=1,#REF!,IF(#REF!=1,#REF!,IF(#REF!=1,#REF!,IF(#REF!=1,#REF!,""))))) -> #REF! | C11: 4 | D11: 51376 | E11: CICERO PEDRO DOS SANTOS | F11: TECNICO DE ELETRICA | G11: CARAPEBUS | H11: CARAPEBUS | I11: CARAPEBUS | J11: CAMINHONETE CABINE SIMPLES | K11: CAMINHONETE CABINE SIMPLES | L11: JEEP CABINE DUPLA 5P
A12: =A11+1 -> 2 | B12: =IF(F12="DESLIGADO","",IF(#REF!=1,#REF!,IF(#REF!=1,#REF!,IF(#REF!=1,#REF!,IF(#REF!=1,#REF!,""))))) -> #REF! | C12: 5 | D12: 52682 | E12: DANIELA DEBORA DE MELO SILVA ANDRADE | F12: AUXILIAR ADMINISTRATIVO DE OBRA I | G12: CARAPEBUS | H12: CARAPEBUS | I12: CARAPEBUS | L12: CAMINHÃO COMBOIO 4X2
A13: =A12+1 -> 3 | B13: =IF(F13="DESLIGADO","",IF(#REF!=1,#REF!,IF(#REF!=1,#REF!,IF(#REF!=1,#REF!,IF(#REF!=1,#REF!,""))))) -> #REF! | C13: 6 | D13: 54531 | E13: THOMAS LEONHARD FONSECA DE SIQUEIRA | F13: AUXILIAR ADMINISTRATIVO DE OBRA I | G13: CARAPEBUS | H13: CARAPEBUS | I13: CARAPEBUS | L13: ESCAVADEIRA HIDRÁULICA SOBRE ESTEIRA
A14: =A13+1 -> 4 | B14: =IF(G14="DESLIGADO","",IF(#REF!=1,#REF!,IF(#REF!=1,#REF!,IF(#REF!=1,#REF!,IF(#REF!=1,#REF!,""))))) -> #REF! | C14: 7 | D14: 46935 | E14: JOSE RENATO DE AGUIAR SOUZA | F14: MOTORISTA DE CAMINHAO/COLETIVO | G14: CARAPEBUS | H14: CARAPEBUS | I14: CARAPEBUS | J14: JEEP CABINE DUPLA 5P | K14: JEEP CABINE DUPLA 5P | L14: TRATOR SOBRE ESTEIRA
A15: =A14+1 -> 5 | B15: =IF(G15="DESLIGADO","",IF(#REF!=1,#REF!,IF(#REF!=1,#REF!,IF(#REF!=1,#REF!,IF(#REF!=1,#REF!,""))))) -> #REF! | C15: 8 | D15: 49752 | E15: EZAQUE ARTHUR SIQUEIRA | F15: AUXILIAR ALMOXARIFADO I | G15: CARAPEBUS | H15: CARAPEBUS | I15: CARAPEBUS | L15: CAMINHAO CABINE AUXILIAR 23 PASSAGEIROS
A16: =A15+1 -> 6 | B16: =IF(G16="DESLIGADO","",IF(#REF!=1,#REF!,IF(#REF!=1,#REF!,IF(#REF!=1,#REF!,IF(#REF!=1,#REF!,""))))) -> #REF! | C16: 9 | D16: 52248 | E16: EMERSON DA SILVA BARBOSA | F16: SERVENTE | G16: CARAPEBUS | H16: CARAPEBUS | I16: CARAPEBUS | L16: CAMINHÃO CARROCERIA 4X4 C/ GUINDAUTO
A17: =A16+1 -> 7 | B17: =IF(G17="DESLIGADO","",IF(#REF!=1,#REF!,IF(#REF!=1,#REF!,IF(#REF!=1,#REF!,IF(#REF!=1,#REF!,""))))) -> #REF! | C17: 10 | D17: PJ -XXS | E17: MARCIO MIRANDA FONSECA | F17: ANALISTA TÉCNICO II | G17: CARAPEBUS | H17: CARAPEBUS | I17: CARAPEBUS | L17: TRATOR SOBRE PNEUS 4X4
A18: =A17+1 -> 8 | B18: =IF(G18="DESLIGADO","",IF(#REF!=1,#REF!,IF(#REF!=1,#REF!,IF(#REF!=1,#REF!,IF(#REF!=1,#REF!,""))))) -> #REF! | C18: 11 | D18: 50652 | E18: DHULLY DA SILVA BELCHIOR | F18: AUXILIAR TECNICO II | G18: CARAPEBUS | H18: CARAPEBUS | I18: CARAPEBUS | L18: CAMINHÃO MUNCK 6X4 45 TON
A19: =#REF!+1 -> #REF! | C19: 12 | D19: PJ -20 | E19: HENRIQUE ARRUDA | F19: ENGENHEIRO SEG. DO TRABALHO | G19: CARAPEBUS | H19: CARAPEBUS | I19: CARAPEBUS | J19: CAMINHONETE CABINE DUPLA 4X4 | K19: CAMINHONETE CABINE DUPLA 4X4 | L19: CAMINHÃO CABINE AUXILIAR 23 PASSAGEIROS
A20: =A19+1 -> #REF! | B20: =IF(F20="DESLIGADO","",IF(#REF!=1,#REF!,IF(#REF!=1,#REF!,IF(#REF!=1,#REF!,IF(#REF!=1,#REF!,""))))) -> #REF! | C20: 13 | D20: 45951 | E20: WALDIR RODRIGUES DE OLIVEIRA | F20: TECNICO SEGURANCA TRABALHO SR | G20: CARAPEBUS | H20: CARAPEBUS | I20: CARAPEBUS | J20: CAMINHONETE CABINE DUPLA 4X4 | K20: CAMINHONETE CABINE DUPLA 4X4 | L20: CAMINHÃO PRANCHA 6X4
A21: =A20+1 -> #REF! | B21: =IF(G21="DESLIGADO","",IF(#REF!=1,#REF!,IF(#REF!=1,#REF!,IF(#REF!=1,#REF!,IF(#REF!=1,#REF!,""))))) -> #REF! | C21: 14 | D21: 52208 | E21: ADALBERTO JUNIOR DE MOURA DINIZ | F21: TECNICO DE SEGURANCA DO TRABALHO OBRA PL | G21: CARAPEBUS | H21: CARAPEBUS | I21: CARAPEBUS | L21: CAMINHÃO CARROCERIA 6X4
A22: =A21+1 -> #REF! | B22: =IF(G22="DESLIGADO","",IF(#REF!=1,#REF!,IF(#REF!=1,#REF!,IF(#REF!=1,#REF!,IF(#REF!=1,#REF!,""))))) -> #REF! | C22: 15 | D22: 52126 | E22: REINALDO SANTOS SANTANA | F22: TECNICO DE SEGURANCA DO TRABALHO OBRA PL | G22: CARAPEBUS | H22: CARAPEBUS | I22: CARAPEBUS | L22: CAMINHÃO BETONEIRA
A23: =A22+1 -> #REF! | C23: 16 | D23: 49173 | E23: MANOEL CARLOS SILVA FRANCA | F23: TECNICO AMBIENTAL SR | G23: CARAPEBUS | H23: CARAPEBUS | I23: CARAPEBUS | J23: CAMINHONETE CABINE DUPLA 4X4 | K23: CAMINHONETE CABINE DUPLA 4X4 | L23: VEICULO LEVE
A24: =A23+1 -> #REF! | B24: =IF(G24="DESLIGADO","",IF(#REF!=1,#REF!,IF(#REF!=1,#REF!,IF(#REF!=1,#REF!,IF(#REF!=1,#REF!,""))))) -> #REF! | C24: 17 | D24: 51876 | E24: JOAO SILVA DE LIMA | F24: MOTORISTA DE AMBULANCIA | G24: CARAPEBUS | H24: CARAPEBUS | I24: CARAPEBUS | L24: CAMINHONETE L200 TRITON 4X4
A25: =A24+1 -> #REF! | B25: =IF(G25="DESLIGADO","",IF(#REF!=1,#REF!,IF(#REF!=1,#REF!,IF(#REF!=1,#REF!,IF(#REF!=1,#REF!,""))))) -> #REF! | C25: 18 | D25: 52113 | E25: EDIVANIA BRITO DE CARVALHO | F25: TECNICO DE ENFERMAGEM DO TRABALHO I | G25: CARAPEBUS | H25: CARAPEBUS | I25: CARAPEBUS | L25: RETROESCAVADEIRA 4X4
A26: =A25+1 -> #REF! | B26: =IF(G26="DESLIGADO","",IF(#REF!=1,#REF!,IF(#REF!=1,#REF!,IF(#REF!=1,#REF!,IF(#REF!=1,#REF!,""))))) -> #REF! | C26: 19 | D26: 52247 | E26: DEBORA CARVALHO VIANNA DE ALMEIDA | F26: AUXILIAR SERVICOS GERAIS OBRA | G26: CARAPEBUS | H26: CARAPEBUS | I26: CARAPEBUS | L26: CARRETA PRANCHA
A27: =A26+1 -> #REF! | B27: =IF(G27="DESLIGADO","",IF(#REF!=1,#REF!,IF(#REF!=1,#REF!,IF(#REF!=1,#REF!,IF(#REF!=1,#REF!,""))))) -> #REF! | C27: 20 | D27: 51918 | E27: ELESILDA GUIMARAES | F27: AUXILIAR SERVICOS GERAIS OBRA | G27: CARAPEBUS | H27: CARAPEBUS | I27: CARAPEBUS | L27: CAMINHÃO PRANCHA 8X4
A28: =A27+1 -> #REF! | B28: =IF(G28="DESLIGADO","",IF(#REF!=1,#REF!,IF(#REF!=1,#REF!,IF(#REF!=1,#REF!,IF(#REF!=1,#REF!,""))))) -> #REF! | C28: 21 | D28: 52206 | E28: MARIA DA GLORIA NASCIMENTO | F28: AUXILIAR SERVICOS GERAIS OBRA | G28: CARAPEBUS | H28: CARAPEBUS | I28: CARAPEBUS | L28: AMBULÂNCIA
A29: =A28+1 -> #REF! | C29: 22 | D29: 53746 | E29: ALEF FELIS DE ANDRADE DOS SANTOS | F29: SERVENTE | G29: CARAPEBUS | H29: CARAPEBUS | I29: CARAPEBUS | L29: CAMINHÃO CABINE AUXILIAR 11 PASSAGEIROS
A30: =A29+1 -> #REF! | B30: =IF(F30="DESLIGADO","",IF(#REF!=1,#REF!,IF(#REF!=1,#REF!,IF(#REF!=1,#REF!,IF(#REF!=1,#REF!,""))))) -> #REF! | C30: 23 | D30: 49937 | E30: LEONARDO BRAGA ALVARENGA | F30: SERVENTE | G30: CARAPEBUS | H30: CARAPEBUS | I30: CARAPEBUS | L30: JEEPÃO 12 PASSAGEIROS
A31: =A30+1 -> #REF! | B31: =IF(G31="DESLIGADO","",IF(#REF!=1,#REF!,IF(#REF!=1,#REF!,IF(#REF!=1,#REF!,IF(#REF!=1,#REF!,""))))) -> #REF! | C31: 24 | D31: 43486 | E31: LEONAN OURIQUE RAMOS | F31: ENCARREGADO DE TRANSPORTES | G31: CARAPEBUS | H31: CARAPEBUS | I31: CARAPEBUS | J31: CAMINHONETE CABINE SIMPLES | K31: CAMINHONETE CABINE SIMPLES | L31: ÔNIBUS 45 PASSAGEIROS
A32: =A31+1 -> #REF! | B32: =IF(G32="DESLIGADO","",IF(#REF!=1,#REF!,IF(#REF!=1,#REF!,IF(#REF!=1,#REF!,IF(#REF!=1,#REF!,""))))) -> #REF! | C32: 25 | D32: 52021 | E32: GABRIEL FOGACA LOPES | F32: AUXILIAR ADMINISTRATIVO DE OBRA I | G32: CARAPEBUS | H32: CARAPEBUS | I32: CARAPEBUS | L32: CAMINHÃO PIPA
A33: =#REF!+1 -> #REF! | B33: =IF(G33="DESLIGADO","",IF(#REF!=1,#REF!,IF(#REF!=1,#REF!,IF(#REF!=1,#REF!,IF(#REF!=1,#REF!,""))))) -> #REF! | C33: 26 | D33: 50636 | E33: LUCIANO GOMES BATISTA | F33: LUBRIFICADOR | G33: CARAPEBUS | H33: CARAPEBUS | I33: CARAPEBUS | L33: CAMINHÃO CABINE AUXILIAR 13 PASSAGEIROS
A34: =A33+1 -> #REF! | B34: =IF(G34="DESLIGADO","",IF(#REF!=1,#REF!,IF(#REF!=1,#REF!,IF(#REF!=1,#REF!,IF(#REF!=1,#REF!,""))))) -> #REF! | C34: 27 | D34: 48851 | E34: ALISON JOSE DA SILVA | F34: MECANICO III | G34: CARAPEBUS | H34: CARAPEBUS | I34: CARAPEBUS | L34: PA CARREGADEIRA
C35: 28 | D35: 50693 | E35: SERGIO MURILO DA SILVA | F35: MOTORISTA DE COMBOIO II | G35: CARAPEBUS | H35: CARAPEBUS | I35: CARAPEBUS | J35: CAMINHÃO COMBOIO 4X2 | K35: CAMINHÃO COMBOIO 4X2
A36: =A35+1 -> 1 | B36: =IF(F36="DESLIGADO","",IF(#REF!=1,#REF!,IF(#REF!=1,#REF!,IF(#REF!=1,#REF!,IF(#REF!=1,#REF!,""))))) -> #REF! | C36: 29 | D36: 49671 | E36: JAQUES DOUGLAS AMARO DA SILVA | F36: LIDER DE TURMA | G36: PÁTIO DE MATERIAIS CARAPEBUS | H36: CARAPEBUS | I36: PÁTIO DE MATERIAIS CARAPEBUS
A37: =A36+1 -> 2 | B37: =IF(G37="DESLIGADO","",IF(#REF!=1,#REF!,IF(#REF!=1,#REF!,IF(#REF!=1,#REF!,IF(#REF!=1,#REF!,""))))) -> #REF! | C37: 30 | D37: 51224 | E37: JOSE OLIVEIRA DOS SANTOS | F37: MONTADOR IV | G37: PÁTIO DE MATERIAIS CARAPEBUS | H37: CARAPEBUS | I37: PÁTIO DE MATERIAIS CARAPEBUS
A38: =A37+1 -> 3 | B38: =IF(G38="DESLIGADO","",IF(#REF!=1,#REF!,IF(#REF!=1,#REF!,IF(#REF!=1,#REF!,IF(#REF!=1,#REF!,""))))) -> #REF! | C38: 31 | D38: 51860 | E38: ALAN SILVA DE SOUZA | F38: OPERADOR DE MAQUINAS III | G38: APOIO LOGÍSTICO | H38: CARAPEBUS | I38: APOIO LOGÍSTICO | J38: ESCAVADEIRA HIDRÁULICA SOBRE ESTEIRA | K38: ESCAVADEIRA HIDRÁULICA SOBRE ESTEIRA
A39: =A38+1 -> 4 | B39: =IF(G39="DESLIGADO","",IF(#REF!=1,#REF!,IF(#REF!=1,#REF!,IF(#REF!=1,#REF!,IF(#REF!=1,#REF!,""))))) -> #REF! | C39: 32 | D39: 53583 | E39: EDVALDO ALVES DIAS | F39: OPERADOR DE MAQUINAS III | G39: APOIO LOGÍSTICO | H39: CARAPEBUS | I39: APOIO LOGÍSTICO | J39: TRATOR SOBRE ESTEIRA | K39: TRATOR SOBRE ESTEIRA
A40: =A39+1 -> 5 | B40: =IF(G40="DESLIGADO","",IF(#REF!=1,#REF!,IF(#REF!=1,#REF!,IF(#REF!=1,#REF!,IF(#REF!=1,#REF!,""))))) -> #REF! | C40: 33 | D40: 54020 | E40: SEVERINO BATISTA DA SILVA | F40: MOTORISTA II | G40: APOIO LOGÍSTICO | H40: CARAPEBUS | I40: APOIO LOGÍSTICO | J40: CAMINHAO CABINE AUXILIAR 23 PASSAGEIROS | K40: CAMINHAO CABINE AUXILIAR 23 PASSAGEIROS
A41: =A40+1 -> 6 | C41: 34 | D41: 51950 | E41: RAIMUNDO GLAUBER GOMES DE SOUSA | F41: ENCARREGADO DE TURMA IV | G41: APOIO CAIXAS DE FUSÃO | H41: CARAPEBUS | I41: APOIO CAIXAS DE FUSÃO
A42: =A41+1 -> 7 | C42: 35 | D42: 53998 | E42: FRANCISCO DAS CHAGAS DE SOUSA CAVALCANTE | F42: MONTADOR III | G42: APOIO CAIXAS DE FUSÃO | H42: CARAPEBUS | I42: APOIO CAIXAS DE FUSÃO
A43: =A42+1 -> 8 | B43: =IF(G43="DESLIGADO","",IF(#REF!=1,#REF!,IF(#REF!=1,#REF!,IF(#REF!=1,#REF!,IF(#REF!=1,#REF!,""))))) -> #REF! | C43: 36 | D43: 53996 | E43: GABRIEL MARINHO MELO | F43: MONTADOR III | G43: APOIO CAIXAS DE FUSÃO | H43: CARAPEBUS | I43: APOIO CAIXAS DE FUSÃO
A44: =A43+1 -> 9 | B44: =IF(F44="DESLIGADO","",IF(#REF!=1,#REF!,IF(#REF!=1,#REF!,IF(#REF!=1,#REF!,IF(#REF!=1,#REF!,""))))) -> #REF! | C44: 37 | D44: 51992 | E44: FABIO RODRIGUES CAMPOS | F44: MONTADOR II | G44: APOIO CAIXAS DE FUSÃO | H44: CARAPEBUS | I44: APOIO CAIXAS DE FUSÃO
A45: =A44+1 -> 10 | B45: =IF(G45="DESLIGADO","",IF(#REF!=1,#REF!,IF(#REF!=1,#REF!,IF(#REF!=1,#REF!,IF(#REF!=1,#REF!,""))))) -> #REF! | C45: 38 | D45: 53425 | E45: DOUGLAS BARBOSA DA SILVA | F45: MONTADOR IV | G45: APOIO CAIXAS DE FUSÃO | H45: CARAPEBUS | I45: APOIO CAIXAS DE FUSÃO
A46: =A45+1 -> 11 | B46: =IF(G46="DESLIGADO","",IF(#REF!=1,#REF!,IF(#REF!=1,#REF!,IF(#REF!=1,#REF!,IF(#REF!=1,#REF!,""))))) -> #REF! | C46: 39 | D46: 52231 | E46: WILSON CARNEIRO DA CUNHA | F46: 1/2 OF. MONTADOR | G46: APOIO CAIXAS DE FUSÃO | H46: CARAPEBUS | I46: APOIO CAIXAS DE FUSÃO
A47: =A46+1 -> 12 | C47: 40 | D47: 54023 | E47: JOHN HENES DA SILVA BATISTA | F47: MOTORISTA II | G47: APOIO CAIXAS DE FUSÃO | H47: CARAPEBUS | I47: APOIO CAIXAS DE FUSÃO | J47: CAMINHÃO CARROCERIA 4X4 C/ GUINDAUTO | K47: CAMINHÃO CARROCERIA 4X4 C/ GUINDAUTO
A48: =A47+1 -> 13 | C48: 41 | D48: 53648 | E48: MAILSON AMORIM BARBOSA | F48: ENCARREGADO DE TURMA III | G48: LANÇAMENTO CABO PILOTO PARA-RAIO/CONDUTOR | H48: CARAPEBUS | I48: LANÇAMENTO CABO PILOTO PARA-RAIO/CONDUTOR
A49: =A48+1 -> 14 | C49: 42 | D49: 53738 | E49: WAENTON DE SIQUEIRA SILVA | F49: OPERADOR TRATOR PNEU II | G49: LANÇAMENTO CABO PILOTO PARA-RAIO/CONDUTOR | H49: CARAPEBUS | I49: LANÇAMENTO CABO PILOTO PARA-RAIO/CONDUTOR | J49: TRATOR SOBRE PNEUS 4X4 | K49: TRATOR SOBRE PNEUS 4X4
A50: =A49+1 -> 15 | B50: =IF(G50="DESLIGADO","",IF(#REF!=1,#REF!,IF(#REF!=1,#REF!,IF(#REF!=1,#REF!,IF(#REF!=1,#REF!,""))))) -> #REF! | C50: 43 | D50: 54029 | E50: JOSEVALDO TENORIO DE FREITAS | F50: MOTORISTA OPERADOR MUNCK III | G50: LANÇAMENTO CABO PILOTO PARA-RAIO/CONDUTOR | H50: CARAPEBUS | I50: LANÇAMENTO CABO PILOTO PARA-RAIO/CONDUTOR | J50: CAMINHÃO MUNCK 6X4 45 TON | K50: CAMINHÃO MUNCK 6X4 45 TON
A51: =A50+1 -> 16 | B51: =IF(G51="DESLIGADO","",IF(#REF!=1,#REF!,IF(#REF!=1,#REF!,IF(#REF!=1,#REF!,IF(#REF!=1,#REF!,""))))) -> #REF! | C51: 44 | D51: 53653 | E51: ANTONIO LUCAS VIEIRA GOMES | F51: MONTADOR III | G51: LANÇAMENTO CABO PILOTO PARA-RAIO/CONDUTOR | H51: CARAPEBUS | I51: LANÇAMENTO CABO PILOTO PARA-RAIO/CONDUTOR
A52: =A51+1 -> 17 | B52: =IF(G52="DESLIGADO","",IF(#REF!=1,#REF!,IF(#REF!=1,#REF!,IF(#REF!=1,#REF!,IF(#REF!=1,#REF!,""))))) -> #REF! | C52: 45 | D52: 53635 | E52: JOSE RODRIGUES GALDINO | F52: MONTADOR II | G52: LANÇAMENTO CABO PILOTO PARA-RAIO/CONDUTOR | H52: CARAPEBUS | I52: LANÇAMENTO CABO PILOTO PARA-RAIO/CONDUTOR
A53: =A52+1 -> 18 | B53: =IF(G53="DESLIGADO","",IF(#REF!=1,#REF!,IF(#REF!=1,#REF!,IF(#REF!=1,#REF!,IF(#REF!=1,#REF!,""))))) -> #REF! | C53: 46 | D53: 53893 | E53: CARLOS ANDRE SOUZA DE JESUS | F53: MONTADOR IV | G53: LANÇAMENTO CABO PILOTO PARA-RAIO/CONDUTOR | H53: CARAPEBUS | I53: LANÇAMENTO CABO PILOTO PARA-RAIO/CONDUTOR
A54: =A53+1 -> 19 | C54: 47 | D54: 53650 | E54: LEANDRO SILVA MARQUES | F54: MONTADOR IV | G54: LANÇAMENTO CABO PILOTO PARA-RAIO/CONDUTOR | H54: CARAPEBUS | I54: LANÇAMENTO CABO PILOTO PARA-RAIO/CONDUTOR
A55: =A54+1 -> 20 | B55: =IF(G55="DESLIGADO","",IF(#REF!=1,#REF!,IF(#REF!=1,#REF!,IF(#REF!=1,#REF!,IF(#REF!=1,#REF!,""))))) -> #REF! | C55: 48 | D55: 53985 | E55: PAULO DE JESUS MARINHO MELO | F55: MONTADOR IV | G55: LANÇAMENTO CABO PILOTO PARA-RAIO/CONDUTOR | H55: CARAPEBUS | I55: LANÇAMENTO CABO PILOTO PARA-RAIO/CONDUTOR
A56: =A55+1 -> 21 | B56: =IF(G56="DESLIGADO","",IF(#REF!=1,#REF!,IF(#REF!=1,#REF!,IF(#REF!=1,#REF!,IF(#REF!=1,#REF!,""))))) -> #REF! | C56: 49 | D56: 53642 | E56: REGINALDO LIMA BARBOSA | F56: MONTADOR IV | G56: LANÇAMENTO CABO PILOTO PARA-RAIO/CONDUTOR | H56: CARAPEBUS | I56: LANÇAMENTO CABO PILOTO PARA-RAIO/CONDUTOR
A57: =A56+1 -> 22 | B57: =IF(G57="DESLIGADO","",IF(#REF!=1,#REF!,IF(#REF!=1,#REF!,IF(#REF!=1,#REF!,IF(#REF!=1,#REF!,""))))) -> #REF! | C57: 50 | D57: 53652 | E57: DEILSON XAVIER MOURA | F57: 1/2 OF. MONTADOR | G57: LANÇAMENTO CABO PILOTO PARA-RAIO/CONDUTOR | H57: CARAPEBUS | I57: LANÇAMENTO CABO PILOTO PARA-RAIO/CONDUTOR
A58: =A57+1 -> 23 | B58: =IF(G58="DESLIGADO","",IF(#REF!=1,#REF!,IF(#REF!=1,#REF!,IF(#REF!=1,#REF!,IF(#REF!=1,#REF!,""))))) -> #REF! | C58: 51 | D58: 53651 | E58: MARCOS FONSECA DE LIMA | F58: 1/2 OF. MONTADOR | G58: LANÇAMENTO CABO PILOTO PARA-RAIO/CONDUTOR | H58: CARAPEBUS | I58: LANÇAMENTO CABO PILOTO PARA-RAIO/CONDUTOR
A59: =A58+1 -> 24 | B59: =IF(G59="DESLIGADO","",IF(#REF!=1,#REF!,IF(#REF!=1,#REF!,IF(#REF!=1,#REF!,IF(#REF!=1,#REF!,""))))) -> #REF! | C59: 52 | D59: 53649 | E59: WELISON CLEITON CARVALHO | F59: 1/2 OF. MONTADOR | G59: LANÇAMENTO CABO PILOTO PARA-RAIO/CONDUTOR | H59: CARAPEBUS | I59: LANÇAMENTO CABO PILOTO PARA-RAIO/CONDUTOR
A60: =A59+1 -> 25 | B60: =IF(G60="DESLIGADO","",IF(#REF!=1,#REF!,IF(#REF!=1,#REF!,IF(#REF!=1,#REF!,IF(#REF!=1,#REF!,""))))) -> #REF! | C60: 53 | D60: 53802 | E60: EDEUVAN SILVA ALBINO DOS SANTOS | F60: MOTORISTA II | G60: LANÇAMENTO CABO PILOTO PARA-RAIO/CONDUTOR | H60: CARAPEBUS | I60: LANÇAMENTO CABO PILOTO PARA-RAIO/CONDUTOR | J60: CAMINHÃO CABINE AUXILIAR 23 PASSAGEIROS | K60: CAMINHÃO CABINE AUXILIAR 23 PASSAGEIROS
A61: =A60+1 -> 26 | C61: 54 | D61: 53637 | E61: ANTENOR DA SILVA CAVALCANTE | F61: SERVENTE | G61: LANÇAMENTO CABO PILOTO PARA-RAIO/CONDUTOR | H61: CARAPEBUS | I61: LANÇAMENTO CABO PILOTO PARA-RAIO/CONDUTOR
A62: =#REF!+1 -> #REF! | B62: =IF(G62="DESLIGADO","",IF(#REF!=1,#REF!,IF(#REF!=1,#REF!,IF(#REF!=1,#REF!,IF(#REF!=1,#REF!,""))))) -> #REF! | C62: 55 | D62: 53641 | E62: ANTONIO MARCOS BARBOSA DA SILVA | F62: SERVENTE | G62: LANÇAMENTO CABO PILOTO PARA-RAIO/CONDUTOR | H62: CARAPEBUS | I62: LANÇAMENTO CABO PILOTO PARA-RAIO/CONDUTOR
A63: =A62+1 -> #REF! | B63: =IF(G63="DESLIGADO","",IF(#REF!=1,#REF!,IF(#REF!=1,#REF!,IF(#REF!=1,#REF!,IF(#REF!=1,#REF!,""))))) -> #REF! | C63: 56 | D63: 53640 | E63: JOSE ALFREDO DA SILVA SANTOS | F63: SERVENTE | G63: LANÇAMENTO CABO PILOTO PARA-RAIO/CONDUTOR | H63: CARAPEBUS | I63: LANÇAMENTO CABO PILOTO PARA-RAIO/CONDUTOR
A64: =A63+1 -> #REF! | B64: =IF(G64="DESLIGADO","",IF(#REF!=1,#REF!,IF(#REF!=1,#REF!,IF(#REF!=1,#REF!,IF(#REF!=1,#REF!,""))))) -> #REF! | C64: 57 | D64: 53572 | E64: TIAGO BARCELOS DA SILVA | F64: SERVENTE DE PATIO E TRANSPORTE | G64: LANÇAMENTO CABO PILOTO PARA-RAIO/CONDUTOR | H64: CARAPEBUS | I64: LANÇAMENTO CABO PILOTO PARA-RAIO/CONDUTOR
A65: =A64+1 -> #REF! | B65: =IF(G65="DESLIGADO","",IF(#REF!=1,#REF!,IF(#REF!=1,#REF!,IF(#REF!=1,#REF!,IF(#REF!=1,#REF!,""))))) -> #REF! | C65: 58 | D65: 53878 | E65: MARCILIANO DA SILVA LIMA | F65: TOPOGRAFO III | G65: NIVELAMENTO DE OPGW / 3/8" EHS / DOTTEREL E CABOS CONDUTORES | H65: CARAPEBUS | I65: NIVELAMENTO DE OPGW / 3/8" EHS / DOTTEREL E CABOS CONDUTORES
A66: =A65+1 -> #REF! | B66: =IF(G66="DESLIGADO","",IF(#REF!=1,#REF!,IF(#REF!=1,#REF!,IF(#REF!=1,#REF!,IF(#REF!=1,#REF!,""))))) -> #REF! | C66: 59 | D66: 53927 | E66: ANTONIVAL DA SILVA LIMA | F66: NIVELADOR III | G66: NIVELAMENTO DE OPGW / 3/8" EHS / DOTTEREL E CABOS CONDUTORES | H66: CARAPEBUS | I66: NIVELAMENTO DE OPGW / 3/8" EHS / DOTTEREL E CABOS CONDUTORES
A67: =A66+1 -> #REF! | B67: =IF(G67="DESLIGADO","",IF(#REF!=1,#REF!,IF(#REF!=1,#REF!,IF(#REF!=1,#REF!,IF(#REF!=1,#REF!,""))))) -> #REF! | C67: 60 | D67: 53874 | E67: LEANDRO DA SILVA SOUSA | F67: NIVELADOR III | G67: NIVELAMENTO DE OPGW / 3/8" EHS / DOTTEREL E CABOS CONDUTORES | H67: CARAPEBUS | I67: NIVELAMENTO DE OPGW / 3/8" EHS / DOTTEREL E CABOS CONDUTORES
A68: =A67+1 -> #REF! | B68: =IF(G68="DESLIGADO","",IF(#REF!=1,#REF!,IF(#REF!=1,#REF!,IF(#REF!=1,#REF!,IF(#REF!=1,#REF!,""))))) -> #REF! | C68: 61 | D68: 53901 | E68: MATHEUS FRANCISCO DOS SANTOS | F68: NIVELADOR III | G68: NIVELAMENTO DE OPGW / 3/8" EHS / DOTTEREL E CABOS CONDUTORES | H68: CARAPEBUS | I68: NIVELAMENTO DE OPGW / 3/8" EHS / DOTTEREL E CABOS CONDUTORES
A69: =A68+1 -> #REF! | C69: 62 | D69: 53890 | E69: ALFONSO DE SOUSA RABELO MESQUITA | F69: ENCARREGADO DE TURMA II | G69: TRANSPORTE DE BOBINAS / ISOLADORES | H69: CARAPEBUS | I69: TRANSPORTE DE BOBINAS / ISOLADORES
A70: =A69+1 -> #REF! | B70: =IF(G70="DESLIGADO","",IF(#REF!=1,#REF!,IF(#REF!=1,#REF!,IF(#REF!=1,#REF!,IF(#REF!=1,#REF!,""))))) -> #REF! | C70: 63 | D70: 53935 | E70: DEJARINO GOMES DA FONSECA JUNIOR | F70: MOTORISTA OPERADOR MUNCK III | G70: TRANSPORTE DE BOBINAS / ISOLADORES | H70: CARAPEBUS | I70: TRANSPORTE DE BOBINAS / ISOLADORES | J70: CAMINHÃO MUNCK 6X4 45 TON | K70: CAMINHÃO MUNCK 6X4 45 TON
A71: =A70+1 -> #REF! | B71: =IF(G71="DESLIGADO","",IF(#REF!=1,#REF!,IF(#REF!=1,#REF!,IF(#REF!=1,#REF!,IF(#REF!=1,#REF!,""))))) -> #REF! | C71: 64 | D71: 54033 | E71: MARCELO BRITO RANGEL | F71: MOTORISTA CARRETEIRO II | G71: TRANSPORTE DE BOBINAS / ISOLADORES | H71: CARAPEBUS | I71: TRANSPORTE DE BOBINAS / ISOLADORES | J71: CAMINHÃO PRANCHA 6X4 | K71: CAMINHÃO PRANCHA 6X4
A72: =A71+1 -> #REF! | B72: =IF(G72="DESLIGADO","",IF(#REF!=1,#REF!,IF(#REF!=1,#REF!,IF(#REF!=1,#REF!,IF(#REF!=1,#REF!,""))))) -> #REF! | C72: 65 | D72: 53897 | E72: FRANCISCO DAS CHAGAS SILVA DE JESUS | F72: MONTADOR IV | G72: TRANSPORTE DE BOBINAS / ISOLADORES | H72: CARAPEBUS | I72: TRANSPORTE DE BOBINAS / ISOLADORES
A73: =A72+1 -> #REF! | B73: =IF(G73="DESLIGADO","",IF(#REF!=1,#REF!,IF(#REF!=1,#REF!,IF(#REF!=1,#REF!,IF(#REF!=1,#REF!,""))))) -> #REF! | C73: 66 | D73: 53870 | E73: JOSE CLAUDIO SOUSA DA SILVA | F73: MOTORISTA II | G73: TRANSPORTE DE BOBINAS / ISOLADORES | H73: CARAPEBUS | I73: TRANSPORTE DE BOBINAS / ISOLADORES | J73: CAMINHÃO CARROCERIA 6X4 | K73: CAMINHÃO CARROCERIA 6X4
A74: =A73+1 -> #REF! | C74: 67 | D74: 54009 | E74: FELIPE LEITE OLIVEIRA | F74: ENCARREGADO DE TURMA IV | G74: IÇAMENTO DE BANDOLAS / ISOLADORES | H74: CARAPEBUS | I74: IÇAMENTO DE BANDOLAS / ISOLADORES
A75: =A74+1 -> #REF! | C75: 68 | D75: 52213 | E75: NILSON DE SOUZA LEMOS | F75: MOTORISTA OPERADOR BETONEIRA III | G75: IÇAMENTO DE BANDOLAS / ISOLADORES | H75: CARAPEBUS | I75: IÇAMENTO DE BANDOLAS / ISOLADORES | J75: CAMINHÃO BETONEIRA | K75: CAMINHÃO BETONEIRA
A76: =A75+1 -> #REF! | B76: =IF(G76="DESLIGADO","",IF(#REF!=1,#REF!,IF(#REF!=1,#REF!,IF(#REF!=1,#REF!,IF(#REF!=1,#REF!,""))))) -> #REF! | C76: 69 | D76: 54010 | E76: ANTONIO DE SOUSA LIMA | F76: MONTADOR III | G76: IÇAMENTO DE BANDOLAS / ISOLADORES | H76: CARAPEBUS | I76: IÇAMENTO DE BANDOLAS / ISOLADORES
A77: =A76+1 -> #REF! | B77: =IF(F77="DESLIGADO","",IF(#REF!=1,#REF!,IF(#REF!=1,#REF!,IF(#REF!=1,#REF!,IF(#REF!=1,#REF!,""))))) -> #REF! | C77: 70 | D77: 54005 | E77: CLENILSON LEITE DE OLIVEIRA | F77: MONTADOR III | G77: IÇAMENTO DE BANDOLAS / ISOLADORES | H77: CARAPEBUS | I77: IÇAMENTO DE BANDOLAS / ISOLADORES
A78: =A77+1 -> #REF! | B78: =IF(G78="DESLIGADO","",IF(#REF!=1,#REF!,IF(#REF!=1,#REF!,IF(#REF!=1,#REF!,IF(#REF!=1,#REF!,""))))) -> #REF! | C78: 71 | D78: 54007 | E78: IDELBRANDO FRANCISCO DO LIVRAMENTO LEITAO | F78: MONTADOR III | G78: IÇAMENTO DE BANDOLAS / ISOLADORES | H78: CARAPEBUS | I78: IÇAMENTO DE BANDOLAS / ISOLADORES
A79: =A78+1 -> #REF! | B79: =IF(G79="DESLIGADO","",IF(#REF!=1,#REF!,IF(#REF!=1,#REF!,IF(#REF!=1,#REF!,IF(#REF!=1,#REF!,""))))) -> #REF! | C79: 72 | D79: 54006 | E79: ISAAC CARDOZO OLIVEIRA | F79: MONTADOR III | G79: IÇAMENTO DE BANDOLAS / ISOLADORES | H79: CARAPEBUS | I79: IÇAMENTO DE BANDOLAS / ISOLADORES
A80: =A79+1 -> #REF! | B80: =IF(G80="DESLIGADO","",IF(#REF!=1,#REF!,IF(#REF!=1,#REF!,IF(#REF!=1,#REF!,IF(#REF!=1,#REF!,""))))) -> #REF! | C80: 73 | D80: 54011 | E80: ISAEL DA SILVA FONTENELE SOUSA | F80: MONTADOR III | G80: IÇAMENTO DE BANDOLAS / ISOLADORES | H80: CARAPEBUS | I80: IÇAMENTO DE BANDOLAS / ISOLADORES
A81: =A80+1 -> #REF! | C81: 74 | D81: 54008 | E81: PAULO HENRIQUE PEREIRA GARCIA | F81: MONTADOR III | G81: IÇAMENTO DE BANDOLAS / ISOLADORES | H81: CARAPEBUS | I81: IÇAMENTO DE BANDOLAS / ISOLADORES
A82: =A81+1 -> #REF! | B82: =IF(G82="DESLIGADO","",IF(#REF!=1,#REF!,IF(#REF!=1,#REF!,IF(#REF!=1,#REF!,IF(#REF!=1,#REF!,""))))) -> #REF! | C82: 75 | D82: 53862 | E82: HERIBERTO FELICIO DE ARAUJO | F82: MONTADOR IV | G82: IÇAMENTO DE BANDOLAS / ISOLADORES | H82: CARAPEBUS | I82: IÇAMENTO DE BANDOLAS / ISOLADORES
A83: =A82+1 -> #REF! | B83: =IF(G83="DESLIGADO","",IF(#REF!=1,#REF!,IF(#REF!=1,#REF!,IF(#REF!=1,#REF!,IF(#REF!=1,#REF!,""))))) -> #REF! | C83: 76 | D83: 54024 | E83: VANCLEILDO DA SILVA SOUZA | F83: OPERADOR TRATOR PNEU III | G83: IÇAMENTO DE BANDOLAS / ISOLADORES | H83: CARAPEBUS | I83: IÇAMENTO DE BANDOLAS / ISOLADORES
A84: =A83+1 -> #REF! | B84: =IF(G84="DESLIGADO","",IF(#REF!=1,#REF!,IF(#REF!=1,#REF!,IF(#REF!=1,#REF!,IF(#REF!=1,#REF!,""))))) -> #REF! | C84: 77 | D84: 54012 | E84: EDIVALDO ALVES NASCIMENTO | F84: ENCARREGADO DE TURMA III | G84: LANÇAMENTO CONDUTORES - ARRAIA | H84: CARAPEBUS | I84: LANÇAMENTO CONDUTORES - ARRAIA
A85: =#REF!+1 -> #REF! | B85: =IF(G85="DESLIGADO","",IF(#REF!=1,#REF!,IF(#REF!=1,#REF!,IF(#REF!=1,#REF!,IF(#REF!=1,#REF!,""))))) -> #REF! | C85: 78 | D85: 54013 | E85: FRANCISCO SALES DE SOUSA AGUIAR JUNIOR | F85: MONTADOR III | G85: LANÇAMENTO CONDUTORES - ARRAIA | H85: CARAPEBUS | I85: LANÇAMENTO CONDUTORES - ARRAIA
A86: =A85+1 -> #REF! | B86: =IF(F86="DESLIGADO","",IF(#REF!=1,#REF!,IF(#REF!=1,#REF!,IF(#REF!=1,#REF!,IF(#REF!=1,#REF!,""))))) -> #REF! | C86: 79 | D86: 54015 | E86: IZAIAS SILVA ALVES | F86: MONTADOR III | G86: LANÇAMENTO CONDUTORES - ARRAIA | H86: CARAPEBUS | I86: LANÇAMENTO CONDUTORES - ARRAIA
A87: =A86+1 -> #REF! | B87: =IF(G87="DESLIGADO","",IF(#REF!=1,#REF!,IF(#REF!=1,#REF!,IF(#REF!=1,#REF!,IF(#REF!=1,#REF!,""))))) -> #REF! | C87: 80 | D87: 54016 | E87: VILMAR ALVES DA SILVA | F87: MONTADOR III | G87: LANÇAMENTO CONDUTORES - ARRAIA | H87: CARAPEBUS | I87: LANÇAMENTO CONDUTORES - ARRAIA
A88: =A87+1 -> #REF! | C88: 81 | D88: TERC-20 | E88: ALEXANDRE RAYMOND | F88: PORTEIRO | G88: VIGILÂNCIA PATRIMONIAL CARAPEBUS | H88: CARAPEBUS | I88: VIGILÂNCIA PATRIMONIAL CARAPEBUS
A89: =A88+1 -> #REF! | B89: =IF(G89="DESLIGADO","",IF(#REF!=1,#REF!,IF(#REF!=1,#REF!,IF(#REF!=1,#REF!,IF(#REF!=1,#REF!,""))))) -> #REF! | C89: 82 | D89: TERC-22 | E89: LEONARDO DIAS PINTO | F89: PORTEIRO | G89: VIGILÂNCIA PATRIMONIAL CARAPEBUS | H89: CARAPEBUS | I89: VIGILÂNCIA PATRIMONIAL CARAPEBUS
A90: =A89+1 -> #REF! | B90: =IF(G90="DESLIGADO","",IF(#REF!=1,#REF!,IF(#REF!=1,#REF!,IF(#REF!=1,#REF!,IF(#REF!=1,#REF!,""))))) -> #REF! | C90: 83 | D90: TERC-21 | E90: MAURICIO REBELO CHAVES | F90: PORTEIRO | G90: VIGILÂNCIA PATRIMONIAL CARAPEBUS | H90: CARAPEBUS | I90: VIGILÂNCIA PATRIMONIAL CARAPEBUS
A91: =A90+1 -> #REF! | B91: =IF(G91="DESLIGADO","",IF(#REF!=1,#REF!,IF(#REF!=1,#REF!,IF(#REF!=1,#REF!,IF(#REF!=1,#REF!,""))))) -> #REF! | C91: 84 | D91: TERC-23 | E91: MIGUEL CANDIDO DOS SANTOS MATOS | F91: PORTEIRO | G91: VIGILÂNCIA PATRIMONIAL CARAPEBUS | H91: CARAPEBUS | I91: VIGILÂNCIA PATRIMONIAL CARAPEBUS
A92: =A91+1 -> #REF! | B92: =IF(G92="DESLIGADO","",IF(#REF!=1,#REF!,IF(#REF!=1,#REF!,IF(#REF!=1,#REF!,IF(#REF!=1,#REF!,""))))) -> #REF! | C92: 85 | D92: 53745 | E92: VALDIR CORREIA SILVA | F92: SERVENTE | G92: VIGILÂNCIA PATRIMONIAL CARAPEBUS | H92: CARAPEBUS | I92: VIGILÂNCIA PATRIMONIAL CARAPEBUS
A93: =A92+1 -> #REF! | B93: =IF(G93="DESLIGADO","",IF(#REF!=1,#REF!,IF(#REF!=1,#REF!,IF(#REF!=1,#REF!,IF(#REF!=1,#REF!,""))))) -> #REF! | C93: 86 | D93: 54483 | E93: VANDERSON DE SOUZA PAULO | F93: VIGIA | G93: VIGILÂNCIA PATRIMONIAL CARAPEBUS | H93: CARAPEBUS | I93: VIGILÂNCIA PATRIMONIAL CARAPEBUS
A94: =A93+1 -> #REF! | C94: 87 | D94: 52243 | E94: WEMERSON LUIZ DE OLIVEIRA PASCOAL | F94: VIGIA | G94: VIGILÂNCIA PATRIMONIAL CARAPEBUS | H94: CARAPEBUS | I94: VIGILÂNCIA PATRIMONIAL CARAPEBUS
A95: =A94+1 -> #REF! | B95: =IF(G95="DESLIGADO","",IF(#REF!=1,#REF!,IF(#REF!=1,#REF!,IF(#REF!=1,#REF!,IF(#REF!=1,#REF!,""))))) -> #REF! | C95: 88 | D95: 49200 | E95: RAIMUNDO NONATO DE SOUSA SILVA | F95: SUBCHEFE DE COZINHA | G95: REFEITÓRIO - TERCEIRIZADOS | H95: CARAPEBUS | I95: REFEITÓRIO - TERCEIRIZADOS
A96: =A95+1 -> #REF! | B96: =IF(G96="DESLIGADO","",IF(#REF!=1,#REF!,IF(#REF!=1,#REF!,IF(#REF!=1,#REF!,IF(#REF!=1,#REF!,""))))) -> #REF! | C96: 89 | D96: 51948 | E96: JHONATAN FREITAS DE SOUZA | F96: MOTORISTA DE VEICULO LEVE | G96: REFEITÓRIO - TERCEIRIZADOS | H96: CARAPEBUS | I96: REFEITÓRIO - TERCEIRIZADOS | J96: VEICULO LEVE | K96: VEICULO LEVE
A97: =A96+1 -> #REF! | B97: =IF(G97="DESLIGADO","",IF(#REF!=1,#REF!,IF(#REF!=1,#REF!,IF(#REF!=1,#REF!,IF(#REF!=1,#REF!,""))))) -> #REF! | C97: 90 | D97: 52045 | E97: ADRIANA NASCIMENTO BRAGA | F97: COZINHEIRA | G97: REFEITÓRIO - TERCEIRIZADOS | H97: CARAPEBUS | I97: REFEITÓRIO - TERCEIRIZADOS
A98: =A97+1 -> #REF! | C98: 91 | D98: 52995 | E98: JACIONE BARBOSA MACHADO | F98: COZINHEIRA | G98: REFEITÓRIO - TERCEIRIZADOS | H98: CARAPEBUS | I98: REFEITÓRIO - TERCEIRIZADOS
A99: =A98+1 -> #REF! | B99: =IF(G99="DESLIGADO","",IF(#REF!=1,#REF!,IF(#REF!=1,#REF!,IF(#REF!=1,#REF!,IF(#REF!=1,#REF!,""))))) -> #REF! | C99: 92 | D99: 52785 | E99: NILDA RODRIGUES AZEVEDO PINTO | F99: AJUDANTE DE COZINHA | G99: REFEITÓRIO - TERCEIRIZADOS | H99: CARAPEBUS | I99: REFEITÓRIO - TERCEIRIZADOS
A100: =A99+1 -> #REF! | C100: 93 | D100: 51949 | E100: RENATA ASSIS SILVA | F100: AJUDANTE DE COZINHA | G100: REFEITÓRIO - TERCEIRIZADOS | H100: CARAPEBUS | I100: REFEITÓRIO - TERCEIRIZADOS
A101: =A100+1 -> #REF! | B101: =IF(G101="DESLIGADO","",IF(#REF!=1,#REF!,IF(#REF!=1,#REF!,IF(#REF!=1,#REF!,IF(#REF!=1,#REF!,""))))) -> #REF! | C101: 94 | D101: 50576 | E101: DANIELA DIAS BATISTA | F101: ASSISTENTE ADMINISTRACAO PESSOAL OBRA PL | G101: AFASTADOS / INSS / LICENÇA | H101: CARAPEBUS | I101: AFASTADOS / INSS / LICENÇA
...

Sheet VEÍCULOS
A1: PLACA | B1: DESCRIÇÃO | C1: MATRICULA | D1: CONDUTOR
A2: SCQ-6B56 | B2: CAMINHONETE CABINE DUPLA 4X4 | C2: PJ - 27 | D2: MENCHOL FREITAS DINIZ
A3: RKZ-0B12 | B3: CAMINHONETE CABINE SIMPLES | C3: 51376 | D3: CICERO PEDRO DOS SANTOS
A4: MUP-1640 | B4: JEEP CABINE DUPLA 5P | C4: 46935 | D4: JOSE RENATO DE AGUIAR SOUZA
A5: SCO-1J16 | B5: CAMINHONETE CABINE DUPLA 4X4 | C5: PJ -20 | D5: HENRIQUE ARRUDA
A6: SCO-1C76 | B6: CAMINHONETE CABINE DUPLA 4X4 | C6: 45951 | D6: WALDIR RODRIGUES DE OLIVEIRA
A7: SCO-1I56 | B7: CAMINHONETE CABINE DUPLA 4X4 | C7: 49173 | D7: MANOEL CARLOS SILVA FRANCA
A8: RVE-8D52 | B8: CAMINHONETE CABINE SIMPLES | C8: 43486 | D8: LEONAN OURIQUE RAMOS
A9: RHB-7G03 | B9: CAMINHÃO COMBOIO 4X2 | C9: 50693 | D9: SERGIO MURILO DA SILVA
A10: EQP-5211 | B10: ESCAVADEIRA HIDRÁULICA SOBRE ESTEIRA | C10: 51860 | D10: ALAN SILVA DE SOUZA
A11: EQP-1046 | B11: TRATOR SOBRE ESTEIRA | C11: 53583 | D11: EDVALDO ALVES DIAS
A12: KJJ-9A85 | B12: CAMINHAO CABINE AUXILIAR 23 PASSAGEIROS | C12: 54020 | D12: SEVERINO BATISTA DA SILVA
A13: EZC-8281 | B13: CAMINHÃO CARROCERIA 4X4 C/ GUINDAUTO | C13: 54023 | D13: JOHN HENES DA SILVA BATISTA
A14: EQP-9109 | B14: TRATOR SOBRE PNEUS 4X4 | C14: 53738 | D14: WAENTON DE SIQUEIRA SILVA
A15: OGI-2H29 | B15: CAMINHÃO MUNCK 6X4 45 TON | C15: 54029 | D15: JOSEVALDO TENORIO DE FREITAS
A16: KIW-9B34 | B16: CAMINHÃO CABINE AUXILIAR 23 PASSAGEIROS | C16: 53802 | D16: EDEUVAN SILVA ALBINO DOS SANTOS
A17: SDS-1G42 | B17: CAMINHÃO MUNCK 6X4 45 TON | C17: 53935 | D17: DEJARINO GOMES DA FONSECA JUNIOR
... A25: EWX-5F92 | B25: CAMINHÃO CARROCERIA 6X4 | C25: 49446 | D25: VALCELI DE OLIVEIRA MENEZES
A26: SCB-3B98 | B26: CAMINHONETE CABINE DUPLA 4X4 | C26: PJ-14 | D26: CLEUBER EDUARDO HEIDEMANN
A27: SCO-3A96 | B27: CAMINHONETE L200 TRITON 4X4 | C27: PJ - 23 | D27: GILBERTO SEVERINO DE LIMA
A28: SCB-3C28 | B28: CAMINHONETE CABINE DUPLA 4X4 | C28: PJ - 26 | D28: KAIK DA SILVA ROCHA
A29: RYL-8J85 | B29: CAMINHONETE CABINE DUPLA 4X4 | C29: 53564 | D29: HUMBERTO SODRE DOS SANTOS NETO
A30: SCO-1D76 | B30: CAMINHONETE CABINE DUPLA 4X4 | C30: 49663 | D30: JOSE EDILSON VIEIRA
A31: QWB-3482 | B31: CAMINHONETE CABINE DUPLA 4X4 | C31: 52644 | D31: RODRIGO DA COSTA QUEIROZ
A32: EQP-7938 | B32: RETROESCAVADEIRA 4X4 | C32: 52077 | D32: ANDRE JOSE FERNANDES JUNIOR
A33: EQP-4208 | B33: ESCAVADEIRA HIDRÁULICA SOBRE ESTEIRA | C33: 53602 | D33: FELIPE LUIZ NASCIMENTO DE BRITO
A34: EQP-5623 | B34: ESCAVADEIRA HIDRÁULICA SOBRE ESTEIRA | C34: 53582 | D34: JOAO INACIO DAS NEVES JUNIOR
A35: NWO-3F49 | B35: CAMINHÃO MUNCK 6X4 45 TON | C35: 53662 | D35: CARLOS ALBERTO NASCIMENTO DE AVIZ
A36: RHG-7A38 | B36: CAMINHÃO MUNCK 6X4 45 TON | C36: 50066 | D36: HILDEBRANDO RIBEIRO DA SILVA
A37: FBO-9C34 | B37: CAMINHÃO MUNCK 6X4 45 TON | C37: 51810 | D37: JOSE WILLAME FERREIRA SANTOS
A38: PWB-3852 | B38: CAMINHÃO MUNCK 6X4 45 TON | C38: 52115 | D38: MANASSES VIANA MATOS
A39: SDX-7G60 | B39: CAMINHÃO MUNCK 6X4 45 TON | C39: 51796 | D39: RAFAEL DE JESUS MARCENA JUNIOR
A40: HDI-7F30 | B40: CARRETA PRANCHA | C40: 51466 | D40: GEORGE FABRICIO FERREIRA DA SILVA
... A55: PEO-6E69 | B55: CAMINHÃO CABINE AUXILIAR 13 PASSAGEIROS | C55: 53784 | D55: THIAGO YURI MARTINS DE ARAUJO
A56: SCO-1B56 | B56: CAMINHONETE CABINE DUPLA 4X4 | C56: PJ - 25 | D56: FABIO DA SILVA PEREIRA
A57: EQP-3010 | B57: RETROESCAVADEIRA 4X4 | C57: 53801 | D57: FABIANO BEZERRA MARINHO
A58: EQP-0456 | B58: PA CARREGADEIRA | C58: 54533 | D58: BRUNO RAFAEL PINHEIRO
A59: SCO-3G16 | B59: CAMINHONETE CABINE DUPLA 4X4 | C59: 40510 | D59: MARCIO LUAN DOS SANTOS
A60: KHX-6H46 | B60: CAMINHÃO CABINE AUXILIAR 23 PASSAGEIROS | C60: 51350 | D60: CRISTIANO SILVA MONTEIRO
A61: MNR-5669 | B61: JEEPÃO 12 PASSAGEIROS | C61: 52023 | D61: JOAO BATISTA DOS SANTOS
A62: PRH-8B56 | B62: CAMINHÃO CABINE AUXILIAR 23 PASSAGEIROS | C62: 54019 | D62: JOSE ERMESON IZIDIO DE LIMA
A63: JIG-1D07 | B63: CAMINHÃO CABINE AUXILIAR 23 PASSAGEIROS | C63: 52251 | D63: JOSE ODILON DA SILVA
A64: EZC-8321 | B64: CAMINHÃO CARROCERIA 6X4 | C64: 51935 | D64: MANOEL MIRANDA BISNETO
A65: JOA-7C60 | B65: CAMINHÃO CABINE AUXILIAR 23 PASSAGEIROS | C65: 52254 | D65: SEVERINO ETELVINO DE OLIVEIRA

Sheet FOTOS
E2: RELATÓRIO DIÁRIO DE OBRA | T2: =LOWER(S2)
B3: ='RDO - Efetivo - Equipamento'!C1 -> OBRA 0474 LT 500 kV TERMINAL RIO - LAGOS
B4: PRAZO CONTRATUAL | E4: DATA | H4: DIA DA SEMANA | K4: RDO No.: | L4: ='Diario de obra'!L4 -> LT-L-TRIO-LGO-RD-A4-00052 | O4: Revisão: | P4: ='Diario de obra'!P4 -> 0A
B5: 219 DIAS | E5: ='RDO - Efetivo - Equipamento'!CA3 -> 45424 | H5: =TEXT(E5,"dddd") -> domingo
B7: EVIDÊNCIAS FOTOGRÁFICAS | S7: =LOWER(R7)
B10: FOTO 1: MOBILIZAÇÃO AMBULÂNCIA | K10: FOTO 2: | S10: =S10 -> 0
B12: FOTO 3: | K12: FOTO 4: | S12: =S12 -> 0
B14: EMPRESA | K14: FISCALIZAÇÂO
B15: DATA: | C15: =+E5 -> 45424 | K15: DATA: | L15: =C15 -> 45424
E16: Assinatura Fasttel | M16: Assinatura Neoenergia

Sheet Datas
B1: Data | C1: RDO nº
B2: 45373 | C2: 1
B3: =B2+1 -> 45374 | C3: 2
B4: =B3+1 -> 45375 | C4: 3
B5: =B4+1 -> 45376 | C5: 4
B6: =B5+1 -> 45377 | C6: 5
B7: =B6+1 -> 45378 | C7: 6
B8: =B7+1 -> 45379 | C8: 7
B9: =B8+1 -> 45380 | C9: 8
B10: =B9+1 -> 45381 | C10: 9
B11: =B10+1 -> 45382 | C11: 10
B12: =B11+1 -> 45383 | C12: 11
B13: =B12+1 -> 45384 | C13: 12
B14: =B13+1 -> 45385 | C14: 13
... B21: =B20+1 -> 45392 | C21: 20
B22: =B21+1 -> 45393 | C22: 21 | E22: 45395
B23: =B22+1 -> 45394 | C23: 22
B24: =B23+1 -> 45395 | C24: 23
B25: =B24+1 -> 45396 | C25: 24
B26: =B25+1 -> 45397 | C26: 25
B27: =B26+1 -> 45398 | C27: 26
B28: =B27+1 -> 45399 | C28: 27
B29: =B28+1 -> 45400 | C29: 28
B30: =B29+1 -> 45401 | C30: 29
B31: =B30+1 -> 45402 | C31: 30
B32: =B31+1 -> 45403 | C32: 31
B33: =B32+1 -> 45404 | C33: 32
B34: =B33+1 -> 45405 | C34: 33
... B1369: =B1368+1 -> 46740 | C1369: 1368

Sheet Anexo 3 "improd chuva
B4: GIRO E PRUMO
B5: CARGOS | C5: QNTD DE PESSOAS | D5: QNTD DE VEÍCULOS | E5: PERIODO
B6: ENCARREGADO DE TURMA IV | C6: 1 | E6: 06:30h as 16:30hs
B7: LIDER DE TURMA | C7: 1 | E7: 06:30h as 16:30hs
B8: MONTADOR III | C8: 1 | E8: 06:30h as 16:30hs
B9: MONTADOR I | C9: 2 | E9: 06:30h as 16:30hs
B10: MONTADOR II | C10: 1 | E10: 06:30h as 16:30hs
B11: MONTADOR IV | C11: 3 | E11: 06:30h as 16:30hs
B12: 1/2 OF. MONTADOR | C12: 1 | E12: 06:30h as 16:30hs
B13: MOTORISTA II | C13: 1 | D13: 1 | E13: 06:30h as 16:30hs
B14: SERVENTE | C14: 2 | E14: 06:30h as 16:30hs
B18: LANÇAMENTO DE CONDUTORES - ARRAIA
B19: CARGOS | C19: QNTD DE PESSOAS | D19: QNTD DE VEÍCULOS | E19: PERIODO
B20: ENCARREGADO DE TURMA I | C20: 1 | E20: 06:30h as 16:30hs
B21: MONTADOR III | C21: 3 | E21: 06:30h as 16:30hs
B25: REVISÃO - ESTAIADAS / AUTOPORTANTES III (5D)
B26: CARGOS | C26: QNTD DE PESSOAS | D26: QNTD DE VEÍCULOS | E26: PERIODO
B27: ENCARREGADO DE TURMA III | C27: 1 | E27: 06:30h as 16:30hs
B28: MONTADOR III | C28: 1 | E28: 06:30h as 16:30hs
B29: MONTADOR II | C29: 2 | E29: 06:30h as 16:30hs
B30: MONTADOR IV | C30: 6 | E30: 06:30h as 16:30hs
B31: 1/2 OF. MONTADOR | C31: 2 | E31: 06:30h as 16:30hs
B32: MOTORISTA II | C32: 1 | D32: 1 | E32: 06:30h as 16:30hs
B33: SERVENTE | C33: 1 | E33: 06:30h as 16:30hs
B37: REVISÃO - ESTAIADAS / AUTOPORTANTES I (5D)
B38: CARGOS | C38: QNTD DE PESSOAS | D38: QNTD DE VEÍCULOS | E38: PERIODO
B39: ENCARREGADO DE TURMA IV | C39: 1 | E39: 06:30h as 16:30hs
B40: MONTADOR III | C40: 2 | E40: 06:30h as 16:30hs
B41: MONTADOR II | C41: 1 | E41: 06:30h as 16:30hs
B42: MONTADOR IV | C42: 5 | E42: 06:30h as 16:30hs
B43: 1/2 OF. MONTADOR | C43: 3 | E43: 06:30h as 16:30hs
B44: MOTORISTA II | C44: 1 | D44: 1 | E44: 06:30h as 16:30hs
B45: SERVENTE | C45: 1 | E45: 06:30h as 16:30hs
B48: REVISÃO - ESTAIADAS / AUTOPORTANTES II (5D)
B49: CARGOS | C49: QNTD DE PESSOAS | D49: QNTD DE VEÍCULOS | E49: PERIODO
B50: ENCARREGADO DE TURMA IV | C50: 1 | E50: 06:30h as 16:30hs
B51: MONTADOR III | C51: 1 | E51: 06:30h as 16:30hs
B52: MONTADOR I | C52: 1 | E52: 06:30h as 16:30hs
B53: MONTADOR II | C53: 3
B54: MONTADOR IV | C54: 6 | E54: 06:30h as 16:30hs
B55: MOTORISTA II | C55: 1 | D55: 1 | E55: 06:30h as 16:30hs
B56: SERVENTE | C56: 3 | E56: 06:30h as 16:30hs
B61: REVISÃO - ESTAIADAS / AUTOPORTANTES IV (5D)
B62: CARGOS | C62: QNTD DE PESSOAS | D62: QNTD DE VEÍCULOS | E62: PERIODO
B63: ENCARREGADO DE TURMA I | C63: 1 | E63: 06:30h as 16:30hs
B64: MONTADOR III | C64: 4 | E64: 06:30h as 16:30hs
B65: MONTADOR II | C65: 1 | E65: 06:30h as 16:30hs
B66: MONTADOR IV | C66: 4 | E66: 06:30h as 16:30hs
B67: 1/2 OF. MONTADOR | C67: 3 | E67: 06:30h as 16:30hs
B68: MOTORISTA II | C68: 1 | D68: 1 | E68: 06:30h as 16:30hs
B69: SERVENTE | C69: 1 | E69: 06:30h as 16:30hs
B73: IÇAMENTO DE BANDOLAS / ISOLADORES
B74: CARGOS | C74: QNTD DE PESSOAS | D74: QNTD DE VEÍCULOS | E74: PERIODO
B75: ENCARREGADO DE TURMA IV | C75: 1 | E75: 06:30h as 16:30hs
B76: MOTORISTA DE CAMINHAO/COLETIVO | C76: 1 | D76: 1 | E76: 06:30h as 16:30hs
B77: MONTADOR III | C77: 6 | E77: 06:30h as 16:30hs
B78: MONTADOR I | C78: 1 | E78: 06:30h as 16:30hs
B79: OPERADOR TRATOR PNEU III | C79: 1 | D79: 1 | E79: 06:30h as 16:30hs
B83: LANÇAMENTO CABO PILOTO PARA-RAIO/CONDUTOR
B84: CARGOS | C84: QNTD DE PESSOAS | D84: QNTD DE VEÍCULOS | E84: PERIODO
B85: ENCARREGADO DE TURMA III | C85: 1 | E85: 06:30h as 16:30hs
B86: OPERADOR TRATOR PNEU II | C86: 1 | D86: 1 | E86: 06:30h as 16:30hs
B87: MOTORISTA OPERADOR MUNCK III | C87: 1 | D87: 1 | E87: 06:30h as 16:30hs
B88: MONTADOR III | C88: 1 | E88: 06:30h as 16:30hs
B89: MONTADOR II | C89: 1 | E89: 06:30h as 16:30hs
B90: MONTADOR IV | C90: 4 | E90: 06:30h as 16:30hs
B91: 1/2 OF. MONTADOR | C91: 3 | E91: 06:30h as 16:30hs
B92: MOTORISTA II | C92: 1 | D92: 1 | E92: 06:30h as 16:30hs
B93: SERVENTE | C93: 4 | E93: 06:30h as 16:30hs
B94: SERVENTE DE PATIO E TRANSPORTE | C94: 1 | E94: 06:30h as 16:30hs

Sheet COMP
A1: Grupo | B1: COD | C1: Nome | D1: Tipo | E1: Cod | F1: Função / Equipamento orçado | G1: Inicio | H1: Fim | I1: Chapa | J1: Nome Completo | K1: Função | L1: Tipo | M1: Canteiro | N1: Empresa | O1: CC | P1: STATUS | R1: Nome_real | S1: Custo_dia_real | T1: Nome_previsto | U1: Custo_dia_previsto
A2: ADMINISTRAÇÃO CAMPOS GOYTACAZES | B2: S/C | C2: GESTÃO DE OBRAS | D2: MO | F2: COORD CONTRATOS | G2: 44652 | H2: 44954 | I2: PJ | J2: LUCAS JOSÉ DE OLIVEIRA | K2: GESTOR DE OBRAS | L2: INDIRETO | M2: CAMPOS DOS GOYTACAZES | N2: PLANOVA | O2: 476 | R2: COORD CONTRATOS | S2: 1680.71 | T2: COORD CONTRATOS | U2: 1680.71 | W2: 44652
A3: ADMINISTRAÇÃO CAMPOS GOYTACAZES | B3: S/C | C3: GESTÃO DE OBRAS | D3: MVE | F3: VEÍCULO LEVE | G3: 44652 | H3: 44954 | I3: RTO-9J24 | J3: VEÍCULO LEVE | L3: INDIRETO | M3: CAMPOS DOS GOYTACAZES | R3: VEÍCULO LEVE | S3: 148.48 | T3: VEÍCULO LEVE | U3: 148.48 | W3: 44652
A4: ADMINISTRAÇÃO CAMPOS GOYTACAZES | B4: S/C | C4: COORDENAÇÃO DE OBRAS | D4: MO | F4: COORD PROJETOS | G4: 44652 | H4: 44954 | I4: PJ-13 | J4: RAFAEL FAGUNDES | K4: COORDENADOR DE OBRAS | L4: INDIRETO | M4: CAMPOS DOS GOYTACAZES | N4: PLANOVA | O4: 474 | R4: COORD PROJETOS | S4: 1376.26 | T4: COORD PROJETOS | U4: 1376.26 | W4: 44652
A5: ADMINISTRAÇÃO CAMPOS GOYTACAZES | B5: S/C | C5: COORDENAÇÃO DE OBRAS | D5: MVE | F5: VEÍCULO LEVE | G5: 44652 | H5: 44954 | I5: FVT-7I73 | J5: VEÍCULO LEVE | L5: INDIRETO | M5: CAMPOS DOS GOYTACAZES | N5: PLANOVA | O5: 476 | R5: VEÍCULO LEVE | S5: 148.48 | T5: VEÍCULO LEVE | U5: 148.48 | W5: 44652
A6: ADMINISTRAÇÃO CAMPOS GOYTACAZES | B6: S/C | C6: PLANEJAMENTO | D6: MO | F6: COORDENADOR DE PLANEJAMENTO | G6: 44652 | H6: 44954 | I6: PJ-10 | J6: MURILO DE ALMEIDA VIEIRA | K6: COORDENADOR DE PLANEJAMENTO | L6: INDIRETO | M6: CAMPOS DOS GOYTACAZES | N6: PLANOVA | O6: 476 | R6: COORDENADOR DE PLANEJAMENTO | S6: 1153.8462 | T6: COORDENADOR DE PLANEJAMENTO | U6: 1153.8462 | W6: 44652
A7: ADMINISTRAÇÃO CAMPOS GOYTACAZES | B7: S/C | C7: PLANEJAMENTO | D7: MO | F7: ANALISTA DE CUSTO I | G7: 44652 | H7: 44954 | I7: PJ-4 | J7: ADELINO RICARDO | K7: ANALISTA DE CUSTO | L7: INDIRETO | M7: CAMPOS DOS GOYTACAZES | N7: PLANOVA | O7: 476 | R7: ANALISTA TECNICO II | S7: 894.47 | T7: ANALISTA DE CUSTO I | U7: 0 | W7: 44652
A8: ADMINISTRAÇÃO CAMPOS GOYTACAZES | B8: S/C | C8: PLANEJAMENTO | D8: MO | G8: 44652 | H8: 44954 | I8: PJ 3 | J8: QUENIO ROGER FERREIRA DOS SANTOS | K8: ANALISTA DE CUSTO I | L8: INDIRETO | M8: CAMPOS DOS GOYTACAZES | N8: PLANOVA | O8: 476 | R8: ANALISTA TECNICO III | S8: 838.03 | T8: 0 | U8: 0 | W8: 44652
A9: ADMINISTRAÇÃO CAMPOS GOYTACAZES | B9: S/C | C9: PLANEJAMENTO | D9: MO | G9: 44652 | H9: 44954 | I9: 50202 | J9: LORENA ALVES DE SOUZA | K9: ASSISTENTE TECNICO PL | L9: INDIRETO | M9: CAMPOS DOS GOYTACAZES | N9: PLANOVA | O9: 476 | R9: ASSIST TECNICO II | S9: 439.24 | T9: 0 | U9: 0 | W9: 44652
A10: ADMINISTRAÇÃO CAMPOS GOYTACAZES | B10: S/C | C10: PROCESSOS | D10: MO | F10: GESTOR DE PROCESSOS | G10: 44652 | H10: 44954 | I10: PJ-14 | J10: JOSÉ ANTONIO BARRETO FILHO | K10: GESTOR DE PROCESSOS | L10: INDIRETO | M10: CAMPOS DOS GOYTACAZES | N10: PLANOVA | O10: SEDE | R10: GESTOR DE PROCESSOS | S10: 749.53348 | T10: GESTOR DE PROCESSOS | U10: 749.53348 | W10: 44652
A11: ADMINISTRAÇÃO CAMPOS GOYTACAZES | B11: S/C | C11: PROCESSOS | D11: MO | F11: ENGENHEIRO DE PLANEJAMENTO II | G11: 44652 | H11: 44954 | I11: PJ-12 | J11: DIEGO JULLIAN DE MORAIS LOPES | K11: ENGENHEIRO DE PROCESSOS | L11: INDIRETO | M11: CAMPOS DOS GOYTACAZES | N11: PLANOVA | O11: 476 | R11: ENGENHEIRO DE PLANEJAMENTO II | S11: 1356.94 | T11: ENGENHEIRO DE PLANEJAMENTO II | U11: 1356.94 | W11: 44652
A12: ADMINISTRAÇÃO CAMPOS GOYTACAZES | B12: S/C | C12: PROCESSOS | D12: MVE | F12: CAMINHONETE 4X4 | G12: 44652 | H12: 44954 | I12: FAA-8372 | J12: CAMINHONETE CD 4X4 | L12: INDIRETO | M12: CAMPOS DOS GOYTACAZES | N12: PLANOVA | O12: 476 | R12: CAMINHONETE 4X4 | S12: 395.5 | T12: CAMINHONETE 4X4 | U12: 395.5 | W12: 44652
A13: ADMINISTRAÇÃO CAMPOS GOYTACAZES | B13: S/C | C13: ADMINISTRAÇÃO | D13: MO | F13: SUPERVISOR ADMINISTRATIVO DE OBRAS | G13: 44652 | H13: 44954 | I13: 48882 | J13: WASHINGTON LUIZ SARTORELLO | K13: SUPERVISOR ADMINISTRATIVO DE OBRAS | L13: INDIRETO | M13: CAMPOS DOS GOYTACAZES | N13: PLANOVA | O13: 476 | R13: SUPERVISOR ADMINISTRATIVO DE OBRAS | S13: 609.74283 | T13: SUPERVISOR ADMINISTRATIVO DE OBRAS | U13: 609.74283 | W13: 44652
A14: ADMINISTRAÇÃO CAMPOS GOYTACAZES | B14: S/C | C14: ADMINISTRAÇÃO | D14: MVE | F14: VEÍCULO LEVE | G14: 44652 | H14: 44954 | I14: FVT-7I13 | J14: VEÍCULO LEVE | L14: INDIRETO | M14: CAMPOS DOS GOYTACAZES | N14: PLANOVA | O14: 476 | R14: VEÍCULO LEVE | S14: 148.48 | T14: VEÍCULO LEVE | U14: 148.48 | W14: 44652
A15: ADMINISTRAÇÃO CAMPOS GOYTACAZES | B15: S/C | C15: ADM/FINANCEIRO | D15: MO | F15: ENC ADMINISTRATIVO - OBRA | G15: 44652 | H15: 44954 | I15: 44279 | J15: ALESON RAUL PEREIRA DE MORAIS | K15: ENCARREGADO ADM OBRAS | L15: INDIRETO | M15: JERÔNIMO MONTEIRO | N15: PLANOVA | O15: 476 | R15: ENC ADMINISTRATIVO - OBRA | S15: 609.74 | T15: ENC ADMINISTRATIVO - OBRA | U15: 609.74 | W15: 44671
A16: ADMINISTRAÇÃO CAMPOS GOYTACAZES | B16: S/C | C16: ADM/FINANCEIRO | D16: MO | F16: ENC ADMINISTRATIVO - OBRA | G16: 44652 | H16: 44954 | I16: 49970 | J16: EDSON PEREIRA DA SILVA | K16: ENCARREGADO ADMINISTRATIVO OBRA JR | L16: INDIRETO | M16: JERÔNIMO MONTEIRO | N16: PLANOVA | O16: 476 | R16: ENC ADMINISTRATIVO - OBRA | S16: 609.74 | T16: ENC ADMINISTRATIVO - OBRA | U16: 609.74 | W16: 44663
A17: ADMINISTRAÇÃO CAMPOS GOYTACAZES | B17: S/C | C17: ADM/FINANCEIRO | D17: MO | F17: ENC ADMINISTRATIVO - OBRA | G17: 44652 | H17: 44954 | I17: 49907 | J17: MANOEL FURQUIM DE CAMARGO NETO | K17: ENCARREGADO ADMINISTRATIVO OBRA JR | L17: INDIRETO | M17: CAMPOS DOS GOYTACAZES | N17: PLANOVA | O17: 476 | R17: ENC ADMINISTRATIVO - OBRA | S17: 609.74 | T17: ENC ADMINISTRATIVO - OBRA | U17: 609.74 | W17: 44652
A18: ADMINISTRAÇÃO CAMPOS GOYTACAZES | B18: S/C | C18: ADM/FINANCEIRO | D18: MO | F18: ASSIST ADMINISTRATIVO PL | G18: 44652 | H18: 44954 | S18: 0 | T18: ASSIST ADMINISTRATIVO PL | U18: 502.04 | W18: 44658
A19: ADMINISTRAÇÃO CAMPOS GOYTACAZES | B19: S/C | C19: ADM/FINANCEIRO | D19: MO | F19: ASSISTENTE ADM DE OBRAS | G19: 44652 | H19: 44954 | I19: 49895 | J19: DANILO DE SOUZA | K19: ASSISTENTE ADMINISTRATIVO OBRA JR | L19: INDIRETO | M19: CAMPOS DOS GOYTACAZES | N19: PLANOVA | O19: 476 | R19: ASSISTENTE ADM DE OBRAS | S19: 297.69 | T19: ASSISTENTE ADM DE OBRAS | U19: 297.69 | W19: 44658
A20: ADMINISTRAÇÃO CAMPOS GOYTACAZES | B20: S/C | C20: ADM/FINANCEIRO | D20: MVE | F20: VEÍCULO LEVE | G20: 44652 | H20: 44954 | I20: CUH-6J28 | J20: VEÍCULO LEVE | L20: INDIRETO | M20: CAMPOS DOS GOYTACAZES | N20: PLANOVA | O20: 476 | R20: VEÍCULO LEVE | S20: 148.48 | T20: VEÍCULO LEVE | U20: 148.48 | W20: 44658
A21: ADMINISTRAÇÃO CAMPOS GOYTACAZES | B21: S/C | C21: ADM/FINANCEIRO | D21: MVE | F21: VEÍCULO LEVE | G21: 44652 | H21: 44954 | I21: RTM-4I20 | J21: VEÍCULO LEVE | L21: INDIRETO | M21: CAMPOS DOS GOYTACAZES | N21: PLANOVA | O21: 476 | R21: VEÍCULO LEVE | S21: 148.48 | T21: VEÍCULO LEVE | U21: 148.48 | W21: 44658
A22: ADMINISTRAÇÃO CAMPOS GOYTACAZES | B22: S/C | C22: ADM/FINANCEIRO | D22: MVE | F22: VEÍCULO LEVE | G22: 44652 | H22: 44954 | S22: 0 | T22: VEÍCULO LEVE | U22: 148.48 | W22: 44658
A23: ADMINISTRAÇÃO CAMPOS GOYTACAZES | B23: S/C | C23: ADM/FINANCEIRO | D23: MVE | F23: VEÍCULO LEVE | G23: 44652 | H23: 44954 | S23: 0 | T23: VEÍCULO LEVE | U23: 148.48 | W23: 44658
A24: ADMINISTRAÇÃO CAMPOS GOYTACAZES | B24: S/C | C24: ADM/FINANCEIRO | D24: MVE | F24: VEÍCULO LEVE | G24: 44652 | H24: 44954 | S24: 0 | T24: VEÍCULO LEVE | U24: 148.48 | W24: 44652
A25: ADMINISTRAÇÃO CAMPOS GOYTACAZES | B25: S/C | C25: ADM/DAP/CLEVER | D25: MO | F25: ENCARREGADO RH SENIOR | G25: 44652 | H25: 44954 | I25: 36712 | J25: JORGE LUIS DA COSTA BARBOSA | K25: ENCARREGADO ADM PESSOAL SR | L25: INDIRETO | M25: CAMPOS DOS GOYTACAZES | N25: PLANOVA | O25: 476 | R25: ENCARREGADO RH SENIOR | S25: 606.95 | T25: ENCARREGADO RH SENIOR | U25: 606.95 | W25: 44679
A26: ADMINISTRAÇÃO CAMPOS GOYTACAZES | B26: S/C | C26: ADM/DAP/CLEVER | D26: MO | F26: ENCARREGADO RH SENIOR | G26: 44652 | H26: 44954 | I26: 50005 | J26: SIDNEY PEREIRA SANTANA | K26: ENCARREGADO ADM PESSOAL JR | L26: INDIRETO | M26: CAMPOS DOS GOYTACAZES | N26: PLANOVA | O26: 476 | R26: ENCARREGADO RH SENIOR | S26: 606.95 | T26: ENCARREGADO RH SENIOR | U26: 606.95 | W26: 44652
A27: ADMINISTRAÇÃO CAMPOS GOYTACAZES | B27: S/C | C27: ADM/DAP/CLEVER | D27: MO | F27: ASSISTENTE ADM DE OBRAS | G27: 44652 | H27: 44954 | I27: 38941 | J27: DIOGO SOUSA CAMPOS | K27: ASSISTENTE DE PESSOAL | L27: INDIRETO | M27: CAMPOS DOS GOYTACAZES | N27: PLANOVA | O27: 476 | R27: ASSISTENTE ADM DE OBRAS | S27: 297.69 | T27: ASSISTENTE ADM DE OBRAS | U27: 297.69 | W27: 44652
A28: ADMINISTRAÇÃO CAMPOS GOYTACAZES | B28: S/C | C28: ADM/DAP/CLEVER | D28: MO | G28: 44652 | H28: 44954 | I28: 48139 | J28: MATEUS ARAUJO MORAIS CHAVES | K28: AUXILIAR ADMINISTRATIVO DE OBRAS | L28: INDIRETO | M28: CAMPOS DOS GOYTACAZES | N28: PLANOVA | O28: 476 | R28: AUX ADMINISTRATIVO I | S28: 247 | T28: 0 | U28: 0 | W28: 44659
A29: ADMINISTRAÇÃO CAMPOS GOYTACAZES | B29: S/C | C29: ADM/DAP/CLEVER | D29: MO | G29: 44652 | H29: 44954 | I29: 50283 | J29: MARCELO GUIMARAES SILVA | K29: AUXILIAR ADMINISTRATIVO DE OBRAS I | L29: INDIRETO | M29: CAMPOS DOS GOYTACAZES | N29: PLANOVA | O29: 476 | R29: AUX ADMINISTRATIVO I | S29: 247 | T29: 0 | U29: 0 | W29: 44652
A30: ADMINISTRAÇÃO CAMPOS GOYTACAZES | B30: S/C | C30: ADM/DAP/CLEVER | D30: MO | F30: AUX ADMINISTRATIVO I | G30: 44652 | H30: 44954 | I30: 49126 | J30: GESLEI LUIZ PEREIRA DA SILVA | K30: AUXILIAR ADMINISTRATIVO DE OBRA III | L30: INDIRETO | M30: CAMPOS DOS GOYTACAZES | N30: PLANOVA | O30: 476 | R30: AUX ADMINISTRATIVO I | S30: 247 | T30: AUX ADMINISTRATIVO I | U30: 247 | W30: 44663
A31: ADMINISTRAÇÃO CAMPOS GOYTACAZES | B31: S/C | C31: ADM/DAP/CLEVER | D31: MO | F31: AUX ADMINISTRATIVO I | G31: 44652 | H31: 44954 | I31: 49891 | J31: ROBERTA SALUCCI PORTELA | K31: AUXILIAR ADMINISTRATIVO DE OBRA III | L31: INDIRETO | M31: JERÔNIMO MONTEIRO | N31: PLANOVA | O31: 476 | R31: AUX ADMINISTRATIVO I | S31: 247 | T31: AUX ADMINISTRATIVO I | U31: 247 | W31: 44652
A32: ADMINISTRAÇÃO CAMPOS GOYTACAZES | B32: S/C | C32: ADM/DAP/CLEVER | D32: MO | F32: AUX ADMINISTRATIVO I | G32: 44652 | H32: 44954 | I32: 49128 | J32: ISABELA RUBATTO RICARDO | K32: AUXILIAR ADMINISTRATIVO DE OBRA II | L32: INDIRETO | M32: CAMPOS DOS GOYTACAZES | N32: PLANOVA | O32: 476 | R32: AUX ADMINISTRATIVO I | S32: 247 | T32: AUX ADMINISTRATIVO I | U32: 247 | W32: 44652
A33: ADMINISTRAÇÃO CAMPOS GOYTACAZES | B33: S/C | C33: ADM/DAP/CLEVER | D33: MO | F33: AUX ADMINISTRATIVO I | G33: 44652 | H33: 44954 | I33: 49920 | J33: LETICIA BASILIO DE SOUZA | K33: AUXILIAR ADMINISTRATIVO DE OBRA I | L33: INDIRETO | M33: CAMPOS DOS GOYTACAZES | N33: PLANOVA | O33: 476 | R33: AUX ADMINISTRATIVO I | S33: 247 | T33: AUX ADMINISTRATIVO I | U33: 247 | W33: 44652
A34: ADMINISTRAÇÃO CAMPOS GOYTACAZES | B34: S/C | C34: ADM/DAP/CLEVER | D34: MO | F34: AUX ADMINISTRATIVO I | G34: 44652 | H34: 44954 | I34: 49635 | J34: STEFANI PEIXOTO GOMES | K34: AUXILIAR ADMINISTRATIVO DE OBRA I | L34: INDIRETO | M34: CAMPOS DOS GOYTACAZES | N34: PLANOVA | O34: 476 | R34: AUX ADMINISTRATIVO I | S34: 247 | T34: AUX ADMINISTRATIVO I | U34: 247 | W34: 44652
A35: ADMINISTRAÇÃO CAMPOS GOYTACAZES | B35: S/C | C35: ADM/DAP/CLEVER | D35: MO | F35: AUX ADMINISTRATIVO I | G35: 44652 | H35: 44954 | I35: 49957 | J35: THERCIO EMANUEL DA SILVA PEREIRA | K35: SERVENTE | L35: INDIRETO | M35: CAMPOS DOS GOYTACAZES | N35: PLANOVA | O35: 476 | R35: SERVENTE | S35: 202.59 | T35: AUX ADMINISTRATIVO I | U35: 247 | W35: 44665
A36: ADMINISTRAÇÃO CAMPOS GOYTACAZES | B36: S/C | C36: ADM/ALMOXARIFADO CAMPOS DOS GOYTACAZES | D36: MO | F36: COMPRADOR DE OBRA SR. | G36: 44652 | H36: 44954 | I36: 48865 | J36: VITOR LUIZ VALENCIO | K36: COMPRADOR DE OBRA SR | L36: INDIRETO | M36: CAMPOS DOS GOYTACAZES | N36: PLANOVA | O36: 476 | R36: COMPRADOR DE OBRA SR. | S36: 535.11 | T36: COMPRADOR DE OBRA SR. | U36: 535.11 | W36: 44652
A37: ADMINISTRAÇÃO CAMPOS GOYTACAZES | B37: S/C | C37: ADM/ALMOXARIFADO CAMPOS DOS GOYTACAZES | D37: MO | F37: COORDENADOR DE ALMOXARIFADO | G37: 44652 | H37: 44954 | I37: PJ-7 | J37: JEAN ROBERTO DOS SANTOS | K37: COORDENADOR DE ALMOXARIFADO | L37: INDIRETO | M37: CAMPOS DOS GOYTACAZES | N37: PLANOVA | O37: 476 | R37: COORDENADOR DE ALMOXARIFADO | S37: 402.26258 | T37: COORDENADOR DE ALMOXARIFADO | U37: 402.26258 | W37: 44652
A38: ADMINISTRAÇÃO CAMPOS GOYTACAZES | B38: S/C | C38: ADM/ALMOXARIFADO CAMPOS DOS GOYTACAZES | D38: MO | F38: ENC ALMOXARIFADO (ENGENHEIRO) | G38: 44652 | H38: 44954 | I38: 49924 | J38: FRANCISCO DE ASSIS AMARAL | K38: ENCARREGADO DE ALMOXARIFADO OBRA SR | L38: INDIRETO | M38: CAMPOS DOS GOYTACAZES | N38: PLANOVA | O38: 476 | R38: ENC ALMOXARIFADO (ENGENHEIRO) | S38: 1029.58 | T38: ENC ALMOXARIFADO (ENGENHEIRO) | U38: 1029.58 | W38: 44671
A39: ADMINISTRAÇÃO CAMPOS GOYTACAZES | B39: S/C | C39: ADM/ALMOXARIFADO CAMPOS DOS GOYTACAZES | D39: MO | F39: ASSIST TECNICO I | G39: 44652 | H39: 44954 | S39: 0 | T39: ASSIST TECNICO I | U39: 285.37 | W39: 44652
A40: ADMINISTRAÇÃO CAMPOS GOYTACAZES | B40: S/C | C40: ADM/ALMOXARIFADO CAMPOS DOS GOYTACAZES | D40: MO | F40: ALMOXARIFE DE OBRA | G40: 44652 | H40: 44954 | I40: 49155 | J40: JOSE ALEXANDRO MONTEIRO DE CARVALHO | K40: ALMOXARIFE I | L40: INDIRETO | M40: CAMPOS DOS GOYTACAZES | N40: PLANOVA | O40: 476 | R40: ALMOXARIFE DE OBRA | S40: 294.55 | T40: ALMOXARIFE DE OBRA | U40: 294.55 | W40: 44677
A41: ADMINISTRAÇÃO CAMPOS GOYTACAZES | B41: S/C | C41: ADM/ALMOXARIFADO CAMPOS DOS GOYTACAZES | D41: MO | F41: ALMOXARIFE DE OBRA | G41: 44652 | H41: 44954 | I41: 49958 | J41: ROBSON RODRIGUES DA SILVA | K41: ALMOXARIFE I | L41: INDIRETO | M41: CAMPOS DOS GOYTACAZES | N41: PLANOVA | O41: 476 | R41: ALMOXARIFE DE OBRA | S41: 294.55 | T41: ALMOXARIFE DE OBRA | U41: 294.55 | W41: 44652
A42: ADMINISTRAÇÃO CAMPOS GOYTACAZES | B42: S/C | C42: ADM/ALMOXARIFADO CAMPOS DOS GOYTACAZES | D42: MO | F42: AUX ALMOXARIFADO - OBRA | G42: 44652 | H42: 44954 | I42: 49233 | J42: ELTON NOGUEIRA ALVES | K42: AUXILIAR ALMOXARIFADO I | L42: INDIRETO | M42: CAMPOS DOS GOYTACAZES | N42: PLANOVA | O42: 476 | R42: AUX ALMOXARIFADO - OBRA | S42: 247.79 | T42: AUX ALMOXARIFADO - OBRA | U42: 247.79 | W42: 44652
A43: ADMINISTRAÇÃO CAMPOS GOYTACAZES | B43: S/C | C43: ADM/ALMOXARIFADO CAMPOS DOS GOYTACAZES | D43: MO | F43: AUX ALMOXARIFADO - OBRA | G43: 44652 | H43: 44954 | I43: 49988 | J43: FRANCIS VIEIRA ROSA | K43: AUXILIAR ALMOXARIFADO I | L43: INDIRETO | M43: CAMPOS DOS GOYTACAZES | N43: PLANOVA | O43: 476 | R43: AUX ALMOXARIFADO - OBRA | S43: 247.79 | T43: AUX ALMOXARIFADO - OBRA | U43: 247.79 | W43: 44652
A44: ADMINISTRAÇÃO CAMPOS GOYTACAZES | B44: S/C | C44: ADM/ALMOXARIFADO CAMPOS DOS GOYTACAZES | D44: MO | F44: MOTORISTA | G44: 44652 | H44: 44954 | I44: 49453 | J44: ALEX DOS SANTOS GOMES | K44: SERVENTE | L44: INDIRETO | M44: CAMPOS DOS GOYTACAZES | N44: PLANOVA | O44: 476 | R44: SERVENTE | S44: 202.59 | T44: MOTORISTA | U44: 0 | W44: 44652
A45: ADMINISTRAÇÃO CAMPOS GOYTACAZES | B45: S/C | C45: ADM/ALMOXARIFADO CAMPOS DOS GOYTACAZES | D45: MO | F45: SERVENTE | G45: 44652 | H45: 44954 | I45: 49514 | J45: ALEX SANDRO BENTO PEIXOTO | K45: SERVENTE | L45: INDIRETO | M45: CAMPOS DOS GOYTACAZES | N45: PLANOVA | O45: 476 | R45: SERVENTE | S45: 202.59 | T45: SERVENTE | U45: 202.59 | W45: 44652
A46: ADMINISTRAÇÃO CAMPOS GOYTACAZES | B46: S/C | C46: ADM/ALMOXARIFADO CAMPOS DOS GOYTACAZES | D46: MO | F46: SERVENTE | G46: 44652 | H46: 44954 | I46: 49450 | J46: ANTONIO MARCOS RAMOS LAZARIO | K46: SERVENTE | L46: INDIRETO | M46: CAMPOS DOS GOYTACAZES | N46: PLANOVA | O46: 476 | R46: SERVENTE | S46: 202.59 | T46: SERVENTE | U46: 202.59 | W46: 44652
A47: ADMINISTRAÇÃO CAMPOS GOYTACAZES | B47: S/C | C47: ADM/ALMOXARIFADO CAMPOS DOS GOYTACAZES | D47: MO | F47: SERVENTE | G47: 44652 | H47: 44954 | I47: 49447 | J47: CARLOS JOSE DOS SANTOS | K47: SERVENTE | L47: INDIRETO | M47: CAMPOS DOS GOYTACAZES | N47: PLANOVA | O47: 476 | R47: SERVENTE | S47: 202.59 | T47: SERVENTE | U47: 202.59 | W47: 44652
A48: ADMINISTRAÇÃO CAMPOS GOYTACAZES | B48: S/C | C48: ADM/ALMOXARIFADO CAMPOS DOS GOYTACAZES | D48: MO | F48: SERVENTE | G48: 44652 | H48: 44954 | I48: 49804 | J48: GEDIEL DE LIMA JUNIOR | K48: SERVENTE | L48: INDIRETO | M48: CAMPOS DOS GOYTACAZES | N48: PLANOVA | O48: 476 | R48: SERVENTE | S48: 202.59 | T48: SERVENTE | U48: 202.59 | W48: 44652
A49: ADMINISTRAÇÃO CAMPOS GOYTACAZES | B49: S/C | C49: ADM/ALMOXARIFADO CAMPOS DOS GOYTACAZES | D49: MO | F49: SERVENTE | G49: 44652 | H49: 44954 | I49: 49485 | J49: JORGE LUIS DA COSTA BARBOSA JUNIOR | K49: SERVENTE | L49: INDIRETO | M49: JERÔNIMO MONTEIRO | N49: PLANOVA | O49: 476 | R49: SERVENTE | S49: 202.59 | T49: SERVENTE | U49: 202.59 | W49: 44652
A50: ADMINISTRAÇÃO CAMPOS GOYTACAZES | B50: S/C | C50: ADM/ALMOXARIFADO CAMPOS DOS GOYTACAZES | D50: MO | F50: SERVENTE | G50: 44652 | H50: 44954 | I50: 49476 | J50: MARCELO PEIXOTO PESSANHA | K50: SERVENTE | L50: INDIRETO | M50: CAMPOS DOS GOYTACAZES | N50: PLANOVA | O50: 476 | R50: SERVENTE | S50: 202.59 | T50: SERVENTE | U50: 202.59 | W50: 44652
A51: ADMINISTRAÇÃO CAMPOS GOYTACAZES | B51: S/C | C51: ADM/ALMOXARIFADO CAMPOS DOS GOYTACAZES | D51: MO | F51: SERVENTE | G51: 44652 | H51: 44954 | I51: 49454 | J51: TARCISIO DOUGLAS BENEDITO DA COSTA | K51: SERVENTE | L51: INDIRETO | M51: CAMPOS DOS GOYTACAZES | N51: PLANOVA | O51: 476 | R51: SERVENTE | S51: 202.59 | T51: SERVENTE | U51: 202.59 | W51: 44652
... A57: MUTUM | B57: S/C | C57: ADM/ALMOXARIFADO MUTUM | D57: MO | F57: SERVENTE | G57: 44652 | H57: 44954 | I57: 49538 | J57: SERGIO MURILO DA SILVA FELIZARDO | K57: SERVENTE | L57: INDIRETO | M57: MUTUM | N57: PLANOVA | O57: 476 | R57: SERVENTE | S57: 202.59 | T57: SERVENTE | U57: 202.59 | W57: 44652
A58: ADMINISTRAÇÃO CAMPOS GOYTACAZES | B58: S/C | C58: SALA TÉCNICA | D58: MO | F58: ANALISTA TECNICO II | G58: 44652 | H58: 44954 | I58: PJ-6 | J58: RAEL SANDRO DO NASCIMENTO | K58: ANALISTA TECNICO | L58: INDIRETO | M58: CAMPOS DOS GOYTACAZES | N58: PLANOVA | O58: 476 | R58: ANALISTA TECNICO II | S58: 894.47 | T58: ANALISTA TECNICO II | U58: 894.47 | W58: 44652
A59: ADMINISTRAÇÃO CAMPOS GOYTACAZES | B59: S/C | C59: SALA TÉCNICA | D59: MO | F59: ANALISTA TECNICO I | G59: 44652 | H59: 44954 | I59: 47377 | J59: WALISSON HUMBERTO DE QUEIROZ PEREIRA | K59: ANALISTA TECNICO DE MATERIAIS I | L59: INDIRETO | M59: CAMPOS DOS GOYTACAZES | N59: PLANOVA | O59: 476 | R59: ANALISTA TECNICO I | S59: 823.09 | T59: ANALISTA TECNICO I | U59: 823.09 | W59: 44652
A60: ADMINISTRAÇÃO CAMPOS GOYTACAZES | B60: S/C | C60: SALA TÉCNICA | D60: MO | F60: TÉCNICO DE QUALIDADE | G60: 44652 | H60: 44954 | I60: 49816 | J60: FERNANDA DANIELLE CASTRO SILVA | K60: TECNICO QUALIDADE SR | L60: INDIRETO | M60: CAMPOS DOS GOYTACAZES | N60: PLANOVA | O60: 476 | R60: TÉCNICO DE QUALIDADE | S60: 436.13 | T60: TÉCNICO DE QUALIDADE | U60: 436.13 | W60: 44652
A61: ADMINISTRAÇÃO CAMPOS GOYTACAZES | B61: S/C | C61: SALA TÉCNICA | D61: MO | F61: ASSIST TECNICO II | G61: 44652 | H61: 44954 | I61: 49350 | J61: LUIZ OTAVIO D'AVILA MARTINS | K61: ASSISTENTE TECNICO SR | L61: INDIRETO | M61: CAMPOS DOS GOYTACAZES | N61: PLANOVA | O61: 476 | R61: ASSIST TECNICO II | S61: 439.24 | T61: ASSIST TECNICO II | U61: 439.24 | W61: 44652
A62: ADMINISTRAÇÃO CAMPOS GOYTACAZES | B62: S/C | C62: SALA TÉCNICA | D62: MO | F62: AUX TECNICO | G62: 44652 | H62: 44954 | I62: 49674 | J62: ROBERTO FLORENCIO SOUSA RODRIGUES | K62: AUXILIAR TECNICO III | L62: INDIRETO | M62: CAMPOS DOS GOYTACAZES | N62: PLANOVA | O62: 476 | R62: AUX TECNICO | S62: 281.55 | T62: AUX TECNICO | U62: 281.55 | W62: 44652
A63: ADMINISTRAÇÃO CAMPOS GOYTACAZES | B63: S/C | C63: SALA TÉCNICA | D63: MO | F63: AUX TECNICO | G63: 44652 | H63: 44954 | I63: 41669 | J63: HYGOR MOREIRA ENVALL | K63: AUXILIAR TECNICO | L63: INDIRETO | M63: JERÔNIMO MONTEIRO | N63: PLANOVA | O63: 476 | R63: AUX TECNICO | S63: 281.55 | T63: AUX TECNICO | U63: 281.55 | W63: 44687
A64: ADMINISTRAÇÃO CAMPOS GOYTACAZES | B64: S/C | C64: QSMS | D64: MO | F64: ENGENHEIRO SEG TRABALHO | G64: 44652 | H64: 44954 | I64: PJ-8 | J64: GILMAR ANTONIO BELLE | K64: ENGENHEIRO SEG. DO TRABALHO | L64: INDIRETO | M64: CAMPOS DOS GOYTACAZES | N64: PLANOVA | O64: 476 | R64: ENGENHEIRO SEG TRABALHO | S64: 944.68 | T64: ENGENHEIRO SEG TRABALHO | U64: 944.68 | W64: 44652
A65: ADMINISTRAÇÃO CAMPOS GOYTACAZES | B65: S/C | C65: QSMS | D65: MO | F65: ENGENHEIRO FLORESTAL II | G65: 44652 | H65: 44954 | I65: PJ-11 | J65: CARLOS ALBERTO GUTERRES CARNEIRO | K65: ENGENHEIRO FLORESTAL II | L65: INDIRETO | M65: CAMPOS DOS GOYTACAZES | N65: PLANOVA | O65: 476 | R65: ENGENHEIRO FLORESTAL II | S65: 944.68 | T65: ENGENHEIRO FLORESTAL II | U65: 944.68 | W65: 44679
A66: ADMINISTRAÇÃO CAMPOS GOYTACAZES | B66: S/C | C66: QSMS | D66: MO | F66: TECNICO SEG TRABALHO III | G66: 44652 | H66: 44954 | I66: 49725 | J66: CARLOS ALBERTO PRATES DE OLIVEIRA | K66: TECNICO SEGURANCA TRABALHO OBRA SR | L66: INDIRETO | M66: CAMPOS DOS GOYTACAZES | N66: PLANOVA | O66: 476 | R66: TECNICO SEG TRABALHO III | S66: 501.48 | T66: TECNICO SEG TRABALHO III | U66: 501.48 | W66: 44671
A67: ADMINISTRAÇÃO CAMPOS GOYTACAZES | B67: S/C | C67: QSMS | D67: MO | F67: TECNICO SEG TRABALHO III | G67: 44652 | H67: 44954 | I67: 50136 | J67: MARCIO AURELIO FURTADO DA SILVA | K67: TECNICO SEGURANCA TRABALHO OBRA SR | L67: INDIRETO | M67: CAMPOS DOS GOYTACAZES | N67: PLANOVA | O67: 476 | R67: TECNICO SEG TRABALHO III | S67: 501.48 | T67: TECNICO SEG TRABALHO III | U67: 501.48 | W67: 44684
A68: ADMINISTRAÇÃO CAMPOS GOYTACAZES | B68: S/C | C68: QSMS | D68: MO | F68: TECNICO SEG TRABALHO III | G68: 44652 | H68: 44954 | I68: 49681 | J68: UELLINTON FERREIRA MOURA | K68: TECNICO SEGURANCA TRABALHO OBRA SR | L68: INDIRETO | M68: CAMPOS DOS GOYTACAZES | N68: PLANOVA | O68: 476 | R68: TECNICO SEG TRABALHO III | S68: 501.48 | T68: TECNICO SEG TRABALHO III | U68: 501.48 | W68: 44652
A69: ADMINISTRAÇÃO CAMPOS GOYTACAZES | B69: S/C | C69: QSMS | D69: MO | F69: TECNICO SEG TRABALHO II | G69: 44652 | H69: 44954 | I69: 49999 | J69: CARLOS ALBERTO ARAUJO STORE | K69: TECNICO SEGURANCA TRABALHO OBRA PL | L69: INDIRETO | M69: CAMPOS DOS GOYTACAZES | N69: PLANOVA | O69: 476 | R69: TECNICO SEG TRABALHO II | S69: 402.26 | T69: TECNICO SEG TRABALHO II | U69: 402.26 | W69: 44659
A70: ADMINISTRAÇÃO CAMPOS GOYTACAZES | B70: S/C | C70: QSMS | D70: MO | F70: TECNICO SEG TRABALHO II | G70: 44652 | H70: 44954 | I70: 49962 | J70: EDNEI MARINO | K70: TECNICO SEGURANCA TRABALHO OBRA PL | L70: INDIRETO | M70: MUTUM | N70: PLANOVA | O70: 476 | R70: TECNICO SEG TRABALHO II | S70: 402.26 | T70: TECNICO SEG TRABALHO II | U70: 402.26 | W70: 44663
A71: ADMINISTRAÇÃO CAMPOS GOYTACAZES | B71: S/C | C71: QSMS | D71: MO | F71: TECNICO SEG TRABALHO II | G71: 44652 | H71: 44954 | I71: 50047 | J71: FABIANO ATAIDE SUCUPIRA | K71: TECNICO SEGURANCA TRABALHO OBRA PL | L71: INDIRETO | M71: JERÔNIMO MONTEIRO | N71: PLANOVA | O71: 476 | R71: TECNICO SEG TRABALHO II | S71: 402.26 | T71: TECNICO SEG TRABALHO II | U71: 402.26 | W71: 44652
A72: ADMINISTRAÇÃO CAMPOS GOYTACAZES | B72: S/C | C72: QSMS | D72: MO | F72: TECNICO SEG TRABALHO II | G72: 44652 | H72: 44954 | I72: 49763 | J72: ROMEU DOS SANTOS | K72: TECNICO SEGURANCA TRABALHO OBRA PL | L72: INDIRETO | M72: JERÔNIMO MONTEIRO | N72: PLANOVA | O72: 476 | R72: TECNICO SEG TRABALHO II | S72: 402.26 | T72: TECNICO SEG TRABALHO II | U72: 402.26 | W72: 44656
A73: ADMINISTRAÇÃO CAMPOS GOYTACAZES | B73: S/C | C73: QSMS | D73: MO | G73: 44652 | H73: 44954 | I73: 49715 | J73: MARINEUDO ASSUNÇÃO | K73: TECNICO SEGURANCA TRABALHO OBRA PL | L73: INDIRETO | M73: CAMPOS DOS GOYTACAZES | N73: PLANOVA | O73: 476 | R73: TECNICO SEG TRABALHO II | S73: 402.26 | T73: 0 | U73: 0 | W73: 44652
A74: ADMINISTRAÇÃO CAMPOS GOYTACAZES | B74: S/C | C74: QSMS | D74: MO | G74: 44652 | H74: 44954 | I74: 50228 | J74: KELSON EMANUEL HONORATO SOUZA | K74: TECNICO SEGURANCA TRABALHO OBRA PL | L74: INDIRETO | M74: MUTUM | N74: PLANOVA | O74: 476 | R74: TECNICO SEG TRABALHO II | S74: 402.26 | T74: 0 | U74: 0 | W74: 44652
A75: ADMINISTRAÇÃO CAMPOS GOYTACAZES | B75: S/C | C75: QSMS | D75: MO | G75: 44652 | H75: 44954 | I75: 48273 | J75: THIAGO OLIVEIRA COTTA | K75: TECNICO DE SEGURANÇA DO TRABALHO JR | L75: INDIRETO | M75: JERÔNIMO MONTEIRO | N75: PLANOVA | O75: 476 | R75: TECNICO SEG TRABALHO II | S75: 402.26 | T75: 0 | U75: 0 | W75: 44692
A76: ADMINISTRAÇÃO CAMPOS GOYTACAZES | B76: S/C | C76: QSMS | D76: MO | F76: TECNICO MEIO AMBIENTE II | G76: 44652 | H76: 44954 | I76: 49892 | J76: CARLOS ALEXANDRE DE SOUZA | K76: TECNICO AMBIENTAL SR | L76: INDIRETO | M76: CAMPOS DOS GOYTACAZES | N76: PLANOVA | O76: 476 | R76: TECNICO MEIO AMBIENTE II | S76: 509.75 | T76: TECNICO MEIO AMBIENTE II | U76: 509.75 | W76: 44684
A77: ADMINISTRAÇÃO CAMPOS GOYTACAZES | B77: S/C | C77: QSMS | D77: MO | F77: TECNICO SEG TRABALHO III | G77: 44652 | H77: 44954 | I77: 49904 | J77: ROSALVO RODRIGUES DA CRUZ JUNIOR | K77: TECNICO AMBIENTAL JR | L77: INDIRETO | M77: CAMPOS DOS GOYTACAZES | N77: PLANOVA | O77: 476 | R77: TECNICO SEG TRABALHO III | S77: 501.48 | T77: TECNICO SEG TRABALHO III | U77: 501.48 | W77: 44652
A78: ADMINISTRAÇÃO CAMPOS GOYTACAZES | B78: S/C | C78: QSMS | D78: MO | F78: TECNICO MEIO AMBIENTE I | G78: 44652 | H78: 44954 | I78: 49173 | J78: MANOEL CARLOS SILVA FRANCA | K78: TECNICO AMBIENTAL JR | L78: INDIRETO | M78: JERÔNIMO MONTEIRO | N78: PLANOVA | O78: 476 | R78: TECNICO SEG TRABALHO III | S78: 501.48 | T78: TECNICO MEIO AMBIENTE I | U78: 353.45 | W78: 44670
A79: ADMINISTRAÇÃO CAMPOS GOYTACAZES | B79: S/C | C79: QSMS | D79: MO | G79: 44652 | H79: 44954 | I79: 50595 | J79: VALTERLANE MIRANDA RIBEIRO | K79: TECNICO AMBIENTAL JR | L79: INDIRETO | M79: CAMPOS DOS GOYTACAZES | N79: PLANOVA | O79: 476 | R79: TECNICO SEG TRABALHO III | S79: 501.48 | T79: 0 | U79: 0 | W79: 44652
A80: ADMINISTRAÇÃO CAMPOS GOYTACAZES | B80: S/C | C80: QSMS | D80: MO | F80: MEDICO DO TRABALHO (BASE 150H) | G80: 44652 | H80: 44954 | I80: 49859 | J80: RICARDO MESQUITA RIBEIRO | K80: MEDICO DO TRABALHO | L80: INDIRETO | M80: CAMPOS DOS GOYTACAZES | N80: PLANOVA | O80: 476 | R80: MEDICO DO TRABALHO (BASE 150H) | S80: 1316.32 | T80: MEDICO DO TRABALHO (BASE 150H) | U80: 1316.32 | W80: 44652
A81: ADMINISTRAÇÃO CAMPOS GOYTACAZES | B81: S/C | C81: QSMS | D81: MO | F81: TÉCNICO DE ENFERMAGEM DO TRAB. II | G81: 44652 | H81: 44954 | I81: 49221 | J81: FAGNER LIMA VALE | K81: TECNICO ENFERMAGEM TRABALHO SR | L81: INDIRETO | M81: CAMPOS DOS GOYTACAZES | N81: PLANOVA | O81: 476 | R81: TÉCNICO DE ENFERMAGEM DO TRAB. II | S81: 0 | T81: TÉCNICO DE ENFERMAGEM DO TRAB. II | U81: 0 | W81: 44652
A82: ADMINISTRAÇÃO CAMPOS GOYTACAZES | B82: S/C | C82: QSMS | D82: MO | F82: TÉCNICO DE ENFERMAGEM DO TRAB. II | G82: 44652 | H82: 44954 | I82: 49724 | J82: ELIANE ANDRADE SIAS | K82: TECNICO ENFERMAGEM TRABALHO PL | L82: INDIRETO | M82: MUTUM | N82: PLANOVA | O82: 476 | R82: TÉCNICO DE ENFERMAGEM DO TRAB. II | S82: 0 | T82: TÉCNICO DE ENFERMAGEM DO TRAB. II | U82: 0 | W82: 44652
A83: ADMINISTRAÇÃO CAMPOS GOYTACAZES | B83: S/C | C83: QSMS | D83: MO | F83: TÉCNICO DE ENFERMAGEM DO TRAB. II | G83: 44652 | H83: 44954 | I83: 50544 | J83: FLAVIO JUNIOR ASSUNCAO | K83: TECNICO ENFERMAGEM TRABALHO PL | L83: INDIRETO | M83: JERÔNIMO MONTEIRO | N83: PLANOVA | O83: 476 | R83: TÉCNICO DE ENFERMAGEM DO TRAB. II | S83: 0 | T83: TÉCNICO DE ENFERMAGEM DO TRAB. II | U83: 0 | W83: 44652
A84: ADMINISTRAÇÃO CAMPOS GOYTACAZES | B84: S/C | C84: QSMS | D84: MO | F84: TÉCNICO DE ENFERMAGEM DO TRAB. II | G84: 44652 | H84: 44954 | I84: 50030 | J84: VILEMAR CARDOSO DE OLIVEIRA | K84: TECNICO ENFERMAGEM DO TRABALHO II | L84: INDIRETO | M84: CAMPOS DOS GOYTACAZES | N84: PLANOVA | O84: 476 | R84: TÉCNICO DE ENFERMAGEM DO TRAB. II | S84: 0 | T84: TÉCNICO DE ENFERMAGEM DO TRAB. II | U84: 0 | W84: 44652
A85: ADMINISTRAÇÃO CAMPOS GOYTACAZES | B85: S/C | C85: QSMS | D85: MO | F85: AUX ADMINISTRATIVO I | G85: 44652 | H85: 44954 | I85: 49124 | J85: LANNA GABRIELA DE OLIVEIRA | K85: AUXILIAR DE SEGURANÇA DO TRABALHO | L85: INDIRETO | M85: CAMPOS DOS GOYTACAZES | N85: PLANOVA | O85: 476 | R85: AUX ADMINISTRATIVO I | S85: 247 | T85: AUX ADMINISTRATIVO I | U85: 247 | W85: 44652
A86: ADMINISTRAÇÃO CAMPOS GOYTACAZES | B86: S/C | C86: QSMS | D86: MO | F86: MOTORISTA CAMINHÃO/COLETIVO | G86: 44652 | H86: 44954 | I86: 49961 | J86: ADEILSON AGNALDO LIMA DE SANTANA | K86: MOTORISTA AMBULANCIA II | L86: INDIRETO | M86: JERÔNIMO MONTEIRO | N86: PLANOVA | O86: 476 | R86: MOTORISTA CAMINHÃO/COLETIVO | S86: 292.54 | T86: MOTORISTA CAMINHÃO/COLETIVO | U86: 292.54 | W86: 44652
A87: ADMINISTRAÇÃO CAMPOS GOYTACAZES | B87: S/C | C87: QSMS | D87: MO | F87: MOTORISTA CAMINHÃO/COLETIVO | G87: 44652 | H87: 44954 | I87: 49517 | J87: JOSE JOAO DA SILVA | K87: MOTORISTA AMBULANCIA II | L87: INDIRETO | M87: MUTUM | N87: PLANOVA | O87: 476 | R87: MOTORISTA CAMINHÃO/COLETIVO | S87: 292.54 | T87: MOTORISTA CAMINHÃO/COLETIVO | U87: 292.54 | W87: 44652
A88: ADMINISTRAÇÃO CAMPOS GOYTACAZES | B88: S/C | C88: QSMS | D88: MO | F88: MOTORISTA CAMINHÃO/COLETIVO | G88: 44652 | H88: 44954 | I88: 49351 | J88: MARCELO SILVIO BEZERRA DA SILVA | K88: MOTORISTA AMBULANCIA II | L88: INDIRETO | M88: CAMPOS DOS GOYTACAZES | N88: PLANOVA | O88: 476 | R88: MOTORISTA CAMINHÃO/COLETIVO | S88: 292.54 | T88: MOTORISTA CAMINHÃO/COLETIVO | U88: 292.54 | W88: 44652
A89: ADMINISTRAÇÃO CAMPOS GOYTACAZES | B89: S/C | C89: QSMS | D89: MVE | F89: CAMINHONETE 4X4 | G89: 44652 | H89: 44954 | I89: RTE-1A47 | J89: CAMINHONETE 4X4 | L89: INDIRETO | M89: CAMPOS DOS GOYTACAZES | N89: PLANOVA | O89: 476 | R89: CAMINHONETE 4X4 | S89: 395.5 | T89: CAMINHONETE 4X4 | U89: 395.5 | W89: 44652
A90: ADMINISTRAÇÃO CAMPOS GOYTACAZES | B90: S/C | C90: QSMS | D90: MVE | F90: CAMINHONETE 4X4 | G90: 44652 | H90: 44954 | I90: QPV-0C53 | J90: CAMINHONETE 4X4 | L90: INDIRETO | M90: CAMPOS DOS GOYTACAZES | N90: PLANOVA | O90: 476 | R90: CAMINHONETE 4X4 | S90: 395.5 | T90: CAMINHONETE 4X4 | U90: 395.5 | W90: 44652
A91: ADMINISTRAÇÃO CAMPOS GOYTACAZES | B91: S/C | C91: QSMS | D91: MVE | F91: CAMINHONETE 4X4 | G91: 44652 | H91: 44954 | S91: 0 | T91: CAMINHONETE 4X4 | U91: 395.5 | W91: 44652
A92: ADMINISTRAÇÃO CAMPOS GOYTACAZES | B92: S/C | C92: QSMS | D92: MVE | F92: VEÍCULO LEVE | G92: 44652 | H92: 44954 | I92: EQB-3B51 | J92: VEÍCULO LEVE | L92: INDIRETO | M92: CAMPOS DOS GOYTACAZES | N92: PLANOVA | O92: 476 | R92: VEÍCULO LEVE | S92: 148.48 | T92: VEÍCULO LEVE | U92: 148.48 | W92: 44652
A93: ADMINISTRAÇÃO CAMPOS GOYTACAZES | B93: S/C | C93: QSMS | D93: MVE | F93: VEÍCULO LEVE | G93: 44652 | H93: 44954 | I93: RTO-7H83 | J93: VEÍCULO LEVE | L93: INDIRETO | M93: CAMPOS DOS GOYTACAZES | N93: PLANOVA | O93: 476 | R93: VEÍCULO LEVE | S93: 148.48 | T93: VEÍCULO LEVE | U93: 148.48 | W93: 44685
A94: ADMINISTRAÇÃO CAMPOS GOYTACAZES | B94: S/C | C94: QSMS | D94: MVE | F94: VEÍCULO LEVE | G94: 44652 | H94: 44954 | I94: EBI-9H47 | J94: VEÍCULO LEVE | L94: INDIRETO | M94: CAMPOS DOS GOYTACAZES | N94: PLANOVA | O94: 476 | R94: VEÍCULO LEVE | S94: 148.48 | T94: VEÍCULO LEVE | U94: 148.48 | W94: 44652
A95: ADMINISTRAÇÃO CAMPOS GOYTACAZES | B95: S/C | C95: QSMS | D95: MVE | F95: VEÍCULO LEVE | G95: 44652 | H95: 44954 | S95: 0 | T95: VEÍCULO LEVE | U95: 148.48 | W95: 44652
A96: ADMINISTRAÇÃO CAMPOS GOYTACAZES | B96: S/C | C96: QSMS | D96: MVE | F96: VEÍCULO LEVE | G96: 44652 | H96: 44954 | S96: 0 | T96: VEÍCULO LEVE | U96: 148.48 | W96: 44679
A97: ADMINISTRAÇÃO CAMPOS GOYTACAZES | B97: S/C | C97: QSMS | D97: MVE | F97: VEÍCULO LEVE | G97: 44652 | H97: 44954 | S97: 0 | T97: VEÍCULO LEVE | U97: 148.48 | W97: 44679
A98: ADMINISTRAÇÃO CAMPOS GOYTACAZES | B98: S/C | C98: QSMS | D98: MVE | F98: AMBULÂNCIA | G98: 44652 | H98: 44954 | I98: PIS-8790 | J98: AMBULÂNCIA | L98: INDIRETO | M98: CAMPOS DOS GOYTACAZES | N98: PLANOVA | O98: 476 | R98: AMBULÂNCIA | S98: 456.51 | T98: AMBULÂNCIA | U98: 456.51 | W98: 44679
A99: ADMINISTRAÇÃO CAMPOS GOYTACAZES | B99: S/C | C99: QSMS | D99: MVE | F99: AMBULÂNCIA | G99: 44652 | H99: 44954 | I99: PGR-7J57 | J99: AMBULÂNCIA | L99: INDIRETO | M99: CAMPOS DOS GOYTACAZES | N99: PLANOVA | O99: 476 | R99: AMBULÂNCIA | S99: 456.51 | T99: AMBULÂNCIA | U99: 456.51 | W99: 44652
A100: ADMINISTRAÇÃO CAMPOS GOYTACAZES | B100: S/C | C100: QSMS | D100: MVE | F100: AMBULÂNCIA | G100: 44652 | H100: 44954 | I100: PIW-4950 | J100: AMBULÂNCIA | L100: INDIRETO | M100: CAMPOS DOS GOYTACAZES | N100: PLANOVA | O100: 476 | R100: AMBULÂNCIA | S100: 456.51 | T100: AMBULÂNCIA | U100: 456.51 | W100: 44652
A101: ADMINISTRAÇÃO CAMPOS GOYTACAZES | B101: S/C | C101: ADM/SERVIÇOS GERAIS CAMPOS DOS GOYTACAZES | D101: MO | F101: ENCARREGADO SERV GERAIS | G101: 44652 | H101: 44954 | I101: 50087 | J101: PAULO SERGIO RIBEIRO MOURA | K101: ENCARREGADO DE SERVIÇOS GERAIS | L101: INDIRETO | M101: CAMPOS DOS GOYTACAZES | N101: PLANOVA | O101: 476 | R101: ENCARREGADO SERV GERAIS | S101: 452.03 | T101: ENCARREGADO SERV GERAIS | U101: 452.03 | W101: 44677
A102: ADMINISTRAÇÃO CAMPOS GOYTACAZES | B102: S/C | C102: ADM/SERVIÇOS GERAIS CAMPOS DOS GOYTACAZES | D102: MO | F102: ELETRICISTA | G102: 44652 | H102: 44954 | I102: 49675 | J102: DARY RIBEIRO DOS SANTOS | K102: ELETRICISTA III | L102: INDIRETO | M102: CAMPOS DOS GOYTACAZES | N102: PLANOVA | O102: 476 | R102: ELETRICISTA | S102: 275.25 | T102: ELETRICISTA | U102: 275.25 | W102: 44663
A103: ADMINISTRAÇÃO CAMPOS GOYTACAZES | B103: S/C | C103: ADM/SERVIÇOS GERAIS CAMPOS DOS GOYTACAZES | D103: MO | F103: MOTORISTA CAMINHÃO/COLETIVO | G103: 44652 | H103: 44954 | I103: 49149 | J103: FABIO JOSE CABRAL DA SILVA | K103: MOTORISTA DE CAMINHAO/COLETIVO | L103: INDIRETO | M103: CAMPOS DOS GOYTACAZES | N103: PLANOVA | O103: 476 | R103: MOTORISTA CAMINHÃO/COLETIVO | S103: 292.54 | T103: MOTORISTA CAMINHÃO/COLETIVO | U103: 292.54 | W103: 44652
A104: ADMINISTRAÇÃO CAMPOS GOYTACAZES | B104: S/C | C104: ADM/SERVIÇOS GERAIS CAMPOS DOS GOYTACAZES | D104: MO | F104: MOTORISTA CAMINHÃO/COLETIVO | G104: 44652 | H104: 44954 | I104: 49995 | J104: AILTON DE SIQUEIRA SILVA | K104: MOTORISTA I | L104: INDIRETO | M104: CAMPOS DOS GOYTACAZES | N104: PLANOVA | O104: 476 | R104: MOTORISTA CAMINHÃO/COLETIVO | S104: 292.54 | T104: MOTORISTA CAMINHÃO/COLETIVO | U104: 292.54 | W104: 44676
A105: ADMINISTRAÇÃO CAMPOS GOYTACAZES | B105: S/C | C105: ADM/SERVIÇOS GERAIS CAMPOS DOS GOYTACAZES | D105: MO | F105: MOTORISTA CAMINHÃO/COLETIVO | G105: 44652 | H105: 44954 | I105: 49994 | J105: CLEBER GONCALVES DE ARRUDA | K105: MOTORISTA I | L105: INDIRETO | M105: CAMPOS DOS GOYTACAZES | N105: PLANOVA | O105: 476 | R105: MOTORISTA CAMINHÃO/COLETIVO | S105: 292.54 | T105: MOTORISTA CAMINHÃO/COLETIVO | U105: 292.54 | W105: 44658
...
